[
  {
    "countryId": "cn",
    "date": 2023,
    "value": 593896473660.32,
    "indicatorId": "bn-gsr-mrch-cd",
    "rank": 1,
    "decimal": 0
  },
  {
    "countryId": "xc",
    "date": 2023,
    "value": 277567735985.659,
    "indicatorId": "bn-gsr-mrch-cd",
    "rank": 2,
    "decimal": 0
  },
  {
    "countryId": "de",
    "date": 2023,
    "value": 243819046811.723,
    "indicatorId": "bn-gsr-mrch-cd",
    "rank": 3,
    "decimal": 0
  },
  {
    "countryId": "ie",
    "date": 2023,
    "value": 168642819802.719,
    "indicatorId": "bn-gsr-mrch-cd",
    "rank": 4,
    "decimal": 0
  },
  {
    "countryId": "sg",
    "date": 2024,
    "value": 148133409833.612,
    "indicatorId": "bn-gsr-mrch-cd",
    "rank": 5,
    "decimal": 0
  },
  {
    "countryId": "sa",
    "date": 2023,
    "value": 128223901973.635,
    "indicatorId": "bn-gsr-mrch-cd",
    "rank": 6,
    "decimal": 0
  },
  {
    "countryId": "ch",
    "date": 2023,
    "value": 124944386524.036,
    "indicatorId": "bn-gsr-mrch-cd",
    "rank": 7,
    "decimal": 0
  },
  {
    "countryId": "ru",
    "date": 2023,
    "value": 121617353762.116,
    "indicatorId": "bn-gsr-mrch-cd",
    "rank": 8,
    "decimal": 0
  },
  {
    "countryId": "kr",
    "date": 2024,
    "value": 100126900000,
    "indicatorId": "bn-gsr-mrch-cd",
    "rank": 9,
    "decimal": 0
  },
  {
    "countryId": "nl",
    "date": 2023,
    "value": 91986750968.0286,
    "indicatorId": "bn-gsr-mrch-cd",
    "rank": 10,
    "decimal": 0
  },
  {
    "countryId": "no",
    "date": 2024,
    "value": 74098245265.2127,
    "indicatorId": "bn-gsr-mrch-cd",
    "rank": 11,
    "decimal": 0
  },
  {
    "countryId": "qa",
    "date": 2023,
    "value": 68306204109.8709,
    "indicatorId": "bn-gsr-mrch-cd",
    "rank": 12,
    "decimal": 0
  },
  {
    "countryId": "br",
    "date": 2024,
    "value": 65842411265.99,
    "indicatorId": "bn-gsr-mrch-cd",
    "rank": 13,
    "decimal": 0
  },
  {
    "countryId": "kw",
    "date": 2023,
    "value": 51145948030.1433,
    "indicatorId": "bn-gsr-mrch-cd",
    "rank": 14,
    "decimal": 0
  },
  {
    "countryId": "au",
    "date": 2024,
    "value": 45103349938.1519,
    "indicatorId": "bn-gsr-mrch-cd",
    "rank": 15,
    "decimal": 0
  },
  {
    "countryId": "vn",
    "date": 2023,
    "value": 44444000000,
    "indicatorId": "bn-gsr-mrch-cd",
    "rank": 16,
    "decimal": 0
  },
  {
    "countryId": "iq",
    "date": 2023,
    "value": 43196686393.31,
    "indicatorId": "bn-gsr-mrch-cd",
    "rank": 17,
    "decimal": 0
  },
  {
    "countryId": "id",
    "date": 2024,
    "value": 39926442260.1461,
    "indicatorId": "bn-gsr-mrch-cd",
    "rank": 18,
    "decimal": 0
  },
  {
    "countryId": "it",
    "date": 2023,
    "value": 36708772965.4341,
    "indicatorId": "bn-gsr-mrch-cd",
    "rank": 19,
    "decimal": 0
  },
  {
    "countryId": "se",
    "date": 2023,
    "value": 33422264157.2668,
    "indicatorId": "bn-gsr-mrch-cd",
    "rank": 20,
    "decimal": 0
  },
  {
    "countryId": "dk",
    "date": 2023,
    "value": 30213018756.9661,
    "indicatorId": "bn-gsr-mrch-cd",
    "rank": 21,
    "decimal": 0
  },
  {
    "countryId": "my",
    "date": 2024,
    "value": 25666709567.5799,
    "indicatorId": "bn-gsr-mrch-cd",
    "rank": 22,
    "decimal": 0
  },
  {
    "countryId": "om",
    "date": 2023,
    "value": 23844945619.3924,
    "indicatorId": "bn-gsr-mrch-cd",
    "rank": 23,
    "decimal": 0
  },
  {
    "countryId": "ao",
    "date": 2024,
    "value": 22604796439.8859,
    "indicatorId": "bn-gsr-mrch-cd",
    "rank": 24,
    "decimal": 0
  },
  {
    "countryId": "kz",
    "date": 2023,
    "value": 19901001425.152,
    "indicatorId": "bn-gsr-mrch-cd",
    "rank": 25,
    "decimal": 0
  },
  {
    "countryId": "th",
    "date": 2023,
    "value": 19378861451.9449,
    "indicatorId": "bn-gsr-mrch-cd",
    "rank": 26,
    "decimal": 0
  },
  {
    "countryId": "pe",
    "date": 2023,
    "value": 17677992787.2318,
    "indicatorId": "bn-gsr-mrch-cd",
    "rank": 27,
    "decimal": 0
  },
  {
    "countryId": "ly",
    "date": 2021,
    "value": 15339800000,
    "indicatorId": "bn-gsr-mrch-cd",
    "rank": 28,
    "decimal": 0
  },
  {
    "countryId": "cl",
    "date": 2023,
    "value": 15323433158.2753,
    "indicatorId": "bn-gsr-mrch-cd",
    "rank": 29,
    "decimal": 0
  },
  {
    "countryId": "cz",
    "date": 2023,
    "value": 13075215137.935,
    "indicatorId": "bn-gsr-mrch-cd",
    "rank": 30,
    "decimal": 0
  },
  {
    "countryId": "dz",
    "date": 2023,
    "value": 12697502628.694,
    "indicatorId": "bn-gsr-mrch-cd",
    "rank": 31,
    "decimal": 0
  },
  {
    "countryId": "ve",
    "date": 2016,
    "value": 11061000000,
    "indicatorId": "bn-gsr-mrch-cd",
    "rank": 32,
    "decimal": 0
  },
  {
    "countryId": "az",
    "date": 2024,
    "value": 8824944000,
    "indicatorId": "bn-gsr-mrch-cd",
    "rank": 33,
    "decimal": 0
  },
  {
    "countryId": "ng",
    "date": 2023,
    "value": 8075015444.4514,
    "indicatorId": "bn-gsr-mrch-cd",
    "rank": 34,
    "decimal": 0
  },
  {
    "countryId": "pg",
    "date": 2023,
    "value": 7600267418.91572,
    "indicatorId": "bn-gsr-mrch-cd",
    "rank": 35,
    "decimal": 0
  },
  {
    "countryId": "fi",
    "date": 2024,
    "value": 7396910777.05645,
    "indicatorId": "bn-gsr-mrch-cd",
    "rank": 36,
    "decimal": 0
  },
  {
    "countryId": "gy",
    "date": 2023,
    "value": 7207384487.27138,
    "indicatorId": "bn-gsr-mrch-cd",
    "rank": 37,
    "decimal": 0
  },
  {
    "countryId": "gn",
    "date": 2023,
    "value": 6783240000,
    "indicatorId": "bn-gsr-mrch-cd",
    "rank": 38,
    "decimal": 0
  },
  {
    "countryId": "za",
    "date": 2023,
    "value": 5552511398.57538,
    "indicatorId": "bn-gsr-mrch-cd",
    "rank": 39,
    "decimal": 0
  },
  {
    "countryId": "pl",
    "date": 2023,
    "value": 5130000000,
    "indicatorId": "bn-gsr-mrch-cd",
    "rank": 40,
    "decimal": 0
  },
  {
    "countryId": "cg",
    "date": 2021,
    "value": 4732192677.78711,
    "indicatorId": "bn-gsr-mrch-cd",
    "rank": 41,
    "decimal": 0
  },
  {
    "countryId": "mn",
    "date": 2023,
    "value": 4548653044.88741,
    "indicatorId": "bn-gsr-mrch-cd",
    "rank": 42,
    "decimal": 0
  },
  {
    "countryId": "bh",
    "date": 2023,
    "value": 4502659574.46809,
    "indicatorId": "bn-gsr-mrch-cd",
    "rank": 43,
    "decimal": 0
  },
  {
    "countryId": "at",
    "date": 2023,
    "value": 4319404032.93249,
    "indicatorId": "bn-gsr-mrch-cd",
    "rank": 44,
    "decimal": 0
  },
  {
    "countryId": "bn",
    "date": 2023,
    "value": 3799595757.4565,
    "indicatorId": "bn-gsr-mrch-cd",
    "rank": 45,
    "decimal": 0
  },
  {
    "countryId": "tt",
    "date": 2023,
    "value": 3762688995.66811,
    "indicatorId": "bn-gsr-mrch-cd",
    "rank": 46,
    "decimal": 0
  },
  {
    "countryId": "be",
    "date": 2023,
    "value": 3023506866.04759,
    "indicatorId": "bn-gsr-mrch-cd",
    "rank": 47,
    "decimal": 0
  },
  {
    "countryId": "gh",
    "date": 2023,
    "value": 2694516051.27818,
    "indicatorId": "bn-gsr-mrch-cd",
    "rank": 48,
    "decimal": 0
  },
  {
    "countryId": "ec",
    "date": 2023,
    "value": 2206803635.0771,
    "indicatorId": "bn-gsr-mrch-cd",
    "rank": 49,
    "decimal": 0
  },
  {
    "countryId": "uy",
    "date": 2023,
    "value": 2092148573.46206,
    "indicatorId": "bn-gsr-mrch-cd",
    "rank": 50,
    "decimal": 0
  },
  {
    "countryId": "ga",
    "date": 2015,
    "value": 1941269686.48701,
    "indicatorId": "bn-gsr-mrch-cd",
    "rank": 51,
    "decimal": 0
  },
  {
    "countryId": "ss",
    "date": 2023,
    "value": 1763080000,
    "indicatorId": "bn-gsr-mrch-cd",
    "rank": 52,
    "decimal": 0
  },
  {
    "countryId": "cd",
    "date": 2023,
    "value": 1600591230.53808,
    "indicatorId": "bn-gsr-mrch-cd",
    "rank": 53,
    "decimal": 0
  },
  {
    "countryId": "zm",
    "date": 2023,
    "value": 1372853456.29085,
    "indicatorId": "bn-gsr-mrch-cd",
    "rank": 54,
    "decimal": 0
  },
  {
    "countryId": "ci",
    "date": 2022,
    "value": 1074599520.97707,
    "indicatorId": "bn-gsr-mrch-cd",
    "rank": 55,
    "decimal": 0
  },
  {
    "countryId": "sr",
    "date": 2024,
    "value": 931324086.587868,
    "indicatorId": "bn-gsr-mrch-cd",
    "rank": 56,
    "decimal": 0
  },
  {
    "countryId": "la",
    "date": 2023,
    "value": 721175510.433136,
    "indicatorId": "bn-gsr-mrch-cd",
    "rank": 57,
    "decimal": 0
  },
  {
    "countryId": "py",
    "date": 2023,
    "value": 696328255.806553,
    "indicatorId": "bn-gsr-mrch-cd",
    "rank": 58,
    "decimal": 0
  },
  {
    "countryId": "si",
    "date": 2024,
    "value": 644213160.00276,
    "indicatorId": "bn-gsr-mrch-cd",
    "rank": 59,
    "decimal": 0
  },
  {
    "countryId": "sm",
    "date": 2022,
    "value": 404388410.223649,
    "indicatorId": "bn-gsr-mrch-cd",
    "rank": 60,
    "decimal": 0
  },
  {
    "countryId": "sk",
    "date": 2023,
    "value": 323377658.986716,
    "indicatorId": "bn-gsr-mrch-cd",
    "rank": 61,
    "decimal": 0
  },
  {
    "countryId": "bo",
    "date": 2023,
    "value": 261462050.544471,
    "indicatorId": "bn-gsr-mrch-cd",
    "rank": 62,
    "decimal": 0
  },
  {
    "countryId": "sz",
    "date": 2023,
    "value": 167360297.399234,
    "indicatorId": "bn-gsr-mrch-cd",
    "rank": 63,
    "decimal": 0
  },
  {
    "countryId": "hu",
    "date": 2023,
    "value": 77906940.4399814,
    "indicatorId": "bn-gsr-mrch-cd",
    "rank": 64,
    "decimal": 0
  },
  {
    "countryId": "dj",
    "date": 2024,
    "value": 41450096.7943851,
    "indicatorId": "bn-gsr-mrch-cd",
    "rank": 65,
    "decimal": 0
  },
  {
    "countryId": "mh",
    "date": 2021,
    "value": -12305712.597898,
    "indicatorId": "bn-gsr-mrch-cd",
    "rank": 66,
    "decimal": 0
  },
  {
    "countryId": "tv",
    "date": 2022,
    "value": -24057496.6897635,
    "indicatorId": "bn-gsr-mrch-cd",
    "rank": 67,
    "decimal": 0
  },
  {
    "countryId": "nr",
    "date": 2023,
    "value": -57206446.995975,
    "indicatorId": "bn-gsr-mrch-cd",
    "rank": 68,
    "decimal": 0
  },
  {
    "countryId": "ml",
    "date": 2023,
    "value": -74649090.2119965,
    "indicatorId": "bn-gsr-mrch-cd",
    "rank": 69,
    "decimal": 0
  },
  {
    "countryId": "bf",
    "date": 2023,
    "value": -93503492.9314881,
    "indicatorId": "bn-gsr-mrch-cd",
    "rank": 70,
    "decimal": 0
  },
  {
    "countryId": "sb",
    "date": 2024,
    "value": -98468458.069037,
    "indicatorId": "bn-gsr-mrch-cd",
    "rank": 71,
    "decimal": 0
  },
  {
    "countryId": "st",
    "date": 2022,
    "value": -142877125.374578,
    "indicatorId": "bn-gsr-mrch-cd",
    "rank": 72,
    "decimal": 0
  },
  {
    "countryId": "tl",
    "date": 2023,
    "value": -149066050.838274,
    "indicatorId": "bn-gsr-mrch-cd",
    "rank": 73,
    "decimal": 0
  },
  {
    "countryId": "gw",
    "date": 2022,
    "value": -153662379.695235,
    "indicatorId": "bn-gsr-mrch-cd",
    "rank": 74,
    "decimal": 0
  },
  {
    "countryId": "pw",
    "date": 2022,
    "value": -156432000,
    "indicatorId": "bn-gsr-mrch-cd",
    "rank": 75,
    "decimal": 0
  },
  {
    "countryId": "mz",
    "date": 2024,
    "value": -163858809.367371,
    "indicatorId": "bn-gsr-mrch-cd",
    "rank": 76,
    "decimal": 0
  },
  {
    "countryId": "ki",
    "date": 2023,
    "value": -184194596.177645,
    "indicatorId": "bn-gsr-mrch-cd",
    "rank": 77,
    "decimal": 0
  },
  {
    "countryId": "to",
    "date": 2024,
    "value": -220990046.414497,
    "indicatorId": "bn-gsr-mrch-cd",
    "rank": 78,
    "decimal": 0
  },
  {
    "countryId": "dm",
    "date": 2023,
    "value": -239520652.592593,
    "indicatorId": "bn-gsr-mrch-cd",
    "rank": 79,
    "decimal": 0
  },
  {
    "countryId": "km",
    "date": 2023,
    "value": -266606464.655837,
    "indicatorId": "bn-gsr-mrch-cd",
    "rank": 80,
    "decimal": 0
  },
  {
    "countryId": "vu",
    "date": 2022,
    "value": -276144342.762252,
    "indicatorId": "bn-gsr-mrch-cd",
    "rank": 81,
    "decimal": 0
  },
  {
    "countryId": "kn",
    "date": 2023,
    "value": -346462375.185185,
    "indicatorId": "bn-gsr-mrch-cd",
    "rank": 82,
    "decimal": 0
  },
  {
    "countryId": "vc",
    "date": 2023,
    "value": -352889494.444444,
    "indicatorId": "bn-gsr-mrch-cd",
    "rank": 83,
    "decimal": 0
  },
  {
    "countryId": "ws",
    "date": 2023,
    "value": -385920923.468947,
    "indicatorId": "bn-gsr-mrch-cd",
    "rank": 84,
    "decimal": 0
  },
  {
    "countryId": "bw",
    "date": 2023,
    "value": -455649769.521256,
    "indicatorId": "bn-gsr-mrch-cd",
    "rank": 85,
    "decimal": 0
  },
  {
    "countryId": "gd",
    "date": 2023,
    "value": -461397132.962963,
    "indicatorId": "bn-gsr-mrch-cd",
    "rank": 86,
    "decimal": 0
  },
  {
    "countryId": "tc",
    "date": 2018,
    "value": -464012400,
    "indicatorId": "bn-gsr-mrch-cd",
    "rank": 87,
    "decimal": 0
  },
  {
    "countryId": "lr",
    "date": 2022,
    "value": -499380380.580711,
    "indicatorId": "bn-gsr-mrch-cd",
    "rank": 88,
    "decimal": 0
  },
  {
    "countryId": "lu",
    "date": 2023,
    "value": -520107448.899638,
    "indicatorId": "bn-gsr-mrch-cd",
    "rank": 89,
    "decimal": 0
  },
  {
    "countryId": "sl",
    "date": 2023,
    "value": -577000000,
    "indicatorId": "bn-gsr-mrch-cd",
    "rank": 90,
    "decimal": 0
  },
  {
    "countryId": "lc",
    "date": 2023,
    "value": -608356287.777778,
    "indicatorId": "bn-gsr-mrch-cd",
    "rank": 91,
    "decimal": 0
  },
  {
    "countryId": "bt",
    "date": 2024,
    "value": -628894316.683173,
    "indicatorId": "bn-gsr-mrch-cd",
    "rank": 92,
    "decimal": 0
  },
  {
    "countryId": "bj",
    "date": 2022,
    "value": -636684456.672714,
    "indicatorId": "bn-gsr-mrch-cd",
    "rank": 93,
    "decimal": 0
  },
  {
    "countryId": "ky",
    "date": 2022,
    "value": -648003968.204775,
    "indicatorId": "bn-gsr-mrch-cd",
    "rank": 94,
    "decimal": 0
  },
  {
    "countryId": "mr",
    "date": 2023,
    "value": -655740780.299098,
    "indicatorId": "bn-gsr-mrch-cd",
    "rank": 95,
    "decimal": 0
  },
  {
    "countryId": "ag",
    "date": 2023,
    "value": -658003023.333333,
    "indicatorId": "bn-gsr-mrch-cd",
    "rank": 96,
    "decimal": 0
  },
  {
    "countryId": "ls",
    "date": 2024,
    "value": -700616749.538893,
    "indicatorId": "bn-gsr-mrch-cd",
    "rank": 97,
    "decimal": 0
  },
  {
    "countryId": "tg",
    "date": 2020,
    "value": -743893212.075397,
    "indicatorId": "bn-gsr-mrch-cd",
    "rank": 98,
    "decimal": 0
  },
  {
    "countryId": "bi",
    "date": 2023,
    "value": -808618247.800965,
    "indicatorId": "bn-gsr-mrch-cd",
    "rank": 99,
    "decimal": 0
  },
  {
    "countryId": "bb",
    "date": 2017,
    "value": -820850907.8558,
    "indicatorId": "bn-gsr-mrch-cd",
    "rank": 100,
    "decimal": 0
  },
  {
    "countryId": "cv",
    "date": 2024,
    "value": -845576461.95076,
    "indicatorId": "bn-gsr-mrch-cd",
    "rank": 101,
    "decimal": 0
  },
  {
    "countryId": "bz",
    "date": 2024,
    "value": -879523647.103447,
    "indicatorId": "bn-gsr-mrch-cd",
    "rank": 102,
    "decimal": 0
  },
  {
    "countryId": "sc",
    "date": 2023,
    "value": -885167612.994735,
    "indicatorId": "bn-gsr-mrch-cd",
    "rank": 103,
    "decimal": 0
  },
  {
    "countryId": "sx",
    "date": 2023,
    "value": -927188776.061453,
    "indicatorId": "bn-gsr-mrch-cd",
    "rank": 104,
    "decimal": 0
  },
  {
    "countryId": "nc",
    "date": 2016,
    "value": -931900356.015228,
    "indicatorId": "bn-gsr-mrch-cd",
    "rank": 105,
    "decimal": 0
  },
  {
    "countryId": "gm",
    "date": 2023,
    "value": -940354218.624603,
    "indicatorId": "bn-gsr-mrch-cd",
    "rank": 106,
    "decimal": 0
  },
  {
    "countryId": "mg",
    "date": 2022,
    "value": -969817246.625245,
    "indicatorId": "bn-gsr-mrch-cd",
    "rank": 107,
    "decimal": 0
  },
  {
    "countryId": "bm",
    "date": 2021,
    "value": -1075954952.83,
    "indicatorId": "bn-gsr-mrch-cd",
    "rank": 108,
    "decimal": 0
  },
  {
    "countryId": "aw",
    "date": 2023,
    "value": -1221450524.39492,
    "indicatorId": "bn-gsr-mrch-cd",
    "rank": 109,
    "decimal": 0
  },
  {
    "countryId": "cw",
    "date": 2023,
    "value": -1269643140.31844,
    "indicatorId": "bn-gsr-mrch-cd",
    "rank": 110,
    "decimal": 0
  },
  {
    "countryId": "pf",
    "date": 2016,
    "value": -1309871446.38518,
    "indicatorId": "bn-gsr-mrch-cd",
    "rank": 111,
    "decimal": 0
  },
  {
    "countryId": "cm",
    "date": 2023,
    "value": -1395930298.24509,
    "indicatorId": "bn-gsr-mrch-cd",
    "rank": 112,
    "decimal": 0
  },
  {
    "countryId": "zw",
    "date": 2023,
    "value": -1452927727.89768,
    "indicatorId": "bn-gsr-mrch-cd",
    "rank": 113,
    "decimal": 0
  },
  {
    "countryId": "ne",
    "date": 2023,
    "value": -1596712941.47965,
    "indicatorId": "bn-gsr-mrch-cd",
    "rank": 114,
    "decimal": 0
  },
  {
    "countryId": "fj",
    "date": 2022,
    "value": -1632033955.81376,
    "indicatorId": "bn-gsr-mrch-cd",
    "rank": 115,
    "decimal": 0
  },
  {
    "countryId": "na",
    "date": 2023,
    "value": -1636167435.54932,
    "indicatorId": "bn-gsr-mrch-cd",
    "rank": 116,
    "decimal": 0
  },
  {
    "countryId": "ad",
    "date": 2023,
    "value": -1646363358.42966,
    "indicatorId": "bn-gsr-mrch-cd",
    "rank": 117,
    "decimal": 0
  },
  {
    "countryId": "mw",
    "date": 2023,
    "value": -1945201027.94975,
    "indicatorId": "bn-gsr-mrch-cd",
    "rank": 118,
    "decimal": 0
  },
  {
    "countryId": "is",
    "date": 2024,
    "value": -2278196556.30061,
    "indicatorId": "bn-gsr-mrch-cd",
    "rank": 119,
    "decimal": 0
  },
  {
    "countryId": "rw",
    "date": 2023,
    "value": -2368759814.47581,
    "indicatorId": "bn-gsr-mrch-cd",
    "rank": 120,
    "decimal": 0
  },
  {
    "countryId": "am",
    "date": 2023,
    "value": -2514652434.25263,
    "indicatorId": "bn-gsr-mrch-cd",
    "rank": 121,
    "decimal": 0
  },
  {
    "countryId": "mt",
    "date": 2023,
    "value": -2646901235.83981,
    "indicatorId": "bn-gsr-mrch-cd",
    "rank": 122,
    "decimal": 0
  },
  {
    "countryId": "ni",
    "date": 2023,
    "value": -2691900000,
    "indicatorId": "bn-gsr-mrch-cd",
    "rank": 123,
    "decimal": 0
  },
  {
    "countryId": "mm",
    "date": 2019,
    "value": -2850333618.52817,
    "indicatorId": "bn-gsr-mrch-cd",
    "rank": 124,
    "decimal": 0
  },
  {
    "countryId": "mv",
    "date": 2023,
    "value": -2874409077.50992,
    "indicatorId": "bn-gsr-mrch-cd",
    "rank": 125,
    "decimal": 0
  },
  {
    "countryId": "ee",
    "date": 2024,
    "value": -2910212732.19429,
    "indicatorId": "bn-gsr-mrch-cd",
    "rank": 126,
    "decimal": 0
  },
  {
    "countryId": "ar",
    "date": 2023,
    "value": -2936850511.3496,
    "indicatorId": "bn-gsr-mrch-cd",
    "rank": 127,
    "decimal": 0
  },
  {
    "countryId": "kh",
    "date": 2023,
    "value": -2986244112.09165,
    "indicatorId": "bn-gsr-mrch-cd",
    "rank": 128,
    "decimal": 0
  },
  {
    "countryId": "ug",
    "date": 2023,
    "value": -3149350000,
    "indicatorId": "bn-gsr-mrch-cd",
    "rank": 129,
    "decimal": 0
  },
  {
    "countryId": "cr",
    "date": 2023,
    "value": -3158381490.94489,
    "indicatorId": "bn-gsr-mrch-cd",
    "rank": 130,
    "decimal": 0
  },
  {
    "countryId": "bs",
    "date": 2023,
    "value": -3213293990.69665,
    "indicatorId": "bn-gsr-mrch-cd",
    "rank": 131,
    "decimal": 0
  },
  {
    "countryId": "mk",
    "date": 2024,
    "value": -3352462152.22908,
    "indicatorId": "bn-gsr-mrch-cd",
    "rank": 132,
    "decimal": 0
  },
  {
    "countryId": "me",
    "date": 2024,
    "value": -3557345717.13028,
    "indicatorId": "bn-gsr-mrch-cd",
    "rank": 133,
    "decimal": 0
  },
  {
    "countryId": "lv",
    "date": 2024,
    "value": -3564936606.71004,
    "indicatorId": "bn-gsr-mrch-cd",
    "rank": 134,
    "decimal": 0
  },
  {
    "countryId": "mu",
    "date": 2023,
    "value": -3600521769.34317,
    "indicatorId": "bn-gsr-mrch-cd",
    "rank": 135,
    "decimal": 0
  },
  {
    "countryId": "ht",
    "date": 2023,
    "value": -3759163824.53355,
    "indicatorId": "bn-gsr-mrch-cd",
    "rank": 136,
    "decimal": 0
  },
  {
    "countryId": "bg",
    "date": 2023,
    "value": -4242940000,
    "indicatorId": "bn-gsr-mrch-cd",
    "rank": 137,
    "decimal": 0
  },
  {
    "countryId": "jm",
    "date": 2023,
    "value": -4399549570.49705,
    "indicatorId": "bn-gsr-mrch-cd",
    "rank": 138,
    "decimal": 0
  },
  {
    "countryId": "tj",
    "date": 2024,
    "value": -4513347235.875,
    "indicatorId": "bn-gsr-mrch-cd",
    "rank": 139,
    "decimal": 0
  },
  {
    "countryId": "by",
    "date": 2024,
    "value": -4700899999.99999,
    "indicatorId": "bn-gsr-mrch-cd",
    "rank": 140,
    "decimal": 0
  },
  {
    "countryId": "md",
    "date": 2023,
    "value": -4869090000,
    "indicatorId": "bn-gsr-mrch-cd",
    "rank": 141,
    "decimal": 0
  },
  {
    "countryId": "lk",
    "date": 2023,
    "value": -4900420616.56074,
    "indicatorId": "bn-gsr-mrch-cd",
    "rank": 142,
    "decimal": 0
  },
  {
    "countryId": "al",
    "date": 2023,
    "value": -4911624603.56604,
    "indicatorId": "bn-gsr-mrch-cd",
    "rank": 143,
    "decimal": 0
  },
  {
    "countryId": "lt",
    "date": 2023,
    "value": -4917575358.19343,
    "indicatorId": "bn-gsr-mrch-cd",
    "rank": 144,
    "decimal": 0
  },
  {
    "countryId": "xk",
    "date": 2023,
    "value": -4973210161.31416,
    "indicatorId": "bn-gsr-mrch-cd",
    "rank": 145,
    "decimal": 0
  },
  {
    "countryId": "ca",
    "date": 2024,
    "value": -5013221844.60609,
    "indicatorId": "bn-gsr-mrch-cd",
    "rank": 146,
    "decimal": 0
  },
  {
    "countryId": "af",
    "date": 2020,
    "value": -5100906449.09748,
    "indicatorId": "bn-gsr-mrch-cd",
    "rank": 147,
    "decimal": 0
  },
  {
    "countryId": "sn",
    "date": 2023,
    "value": -5320568505.20984,
    "indicatorId": "bn-gsr-mrch-cd",
    "rank": 148,
    "decimal": 0
  },
  {
    "countryId": "mx",
    "date": 2023,
    "value": -5548770305.99999,
    "indicatorId": "bn-gsr-mrch-cd",
    "rank": 149,
    "decimal": 0
  },
  {
    "countryId": "sd",
    "date": 2022,
    "value": -5627945772.25282,
    "indicatorId": "bn-gsr-mrch-cd",
    "rank": 150,
    "decimal": 0
  },
  {
    "countryId": "ba",
    "date": 2023,
    "value": -5673713857.07333,
    "indicatorId": "bn-gsr-mrch-cd",
    "rank": 151,
    "decimal": 0
  },
  {
    "countryId": "tz",
    "date": 2023,
    "value": -6032348969.99651,
    "indicatorId": "bn-gsr-mrch-cd",
    "rank": 152,
    "decimal": 0
  },
  {
    "countryId": "ge",
    "date": 2023,
    "value": -6077804691.12,
    "indicatorId": "bn-gsr-mrch-cd",
    "rank": 153,
    "decimal": 0
  },
  {
    "countryId": "ye",
    "date": 2016,
    "value": -6325444800,
    "indicatorId": "bn-gsr-mrch-cd",
    "rank": 154,
    "decimal": 0
  },
  {
    "countryId": "co",
    "date": 2023,
    "value": -6807557955.44131,
    "indicatorId": "bn-gsr-mrch-cd",
    "rank": 155,
    "decimal": 0
  },
  {
    "countryId": "kg",
    "date": 2022,
    "value": -6918726775.26164,
    "indicatorId": "bn-gsr-mrch-cd",
    "rank": 156,
    "decimal": 0
  },
  {
    "countryId": "ps",
    "date": 2023,
    "value": -7121091900.6214,
    "indicatorId": "bn-gsr-mrch-cd",
    "rank": 157,
    "decimal": 0
  },
  {
    "countryId": "rs",
    "date": 2023,
    "value": -7159993128.87172,
    "indicatorId": "bn-gsr-mrch-cd",
    "rank": 158,
    "decimal": 0
  },
  {
    "countryId": "nz",
    "date": 2023,
    "value": -7429995070.7962,
    "indicatorId": "bn-gsr-mrch-cd",
    "rank": 159,
    "decimal": 0
  },
  {
    "countryId": "cy",
    "date": 2023,
    "value": -7785917180.32693,
    "indicatorId": "bn-gsr-mrch-cd",
    "rank": 160,
    "decimal": 0
  },
  {
    "countryId": "hn",
    "date": 2023,
    "value": -8355362068.09267,
    "indicatorId": "bn-gsr-mrch-cd",
    "rank": 161,
    "decimal": 0
  },
  {
    "countryId": "sv",
    "date": 2023,
    "value": -8864731188.14845,
    "indicatorId": "bn-gsr-mrch-cd",
    "rank": 162,
    "decimal": 0
  },
  {
    "countryId": "tn",
    "date": 2023,
    "value": -9052594480.32121,
    "indicatorId": "bn-gsr-mrch-cd",
    "rank": 163,
    "decimal": 0
  },
  {
    "countryId": "ke",
    "date": 2023,
    "value": -10022726294.2824,
    "indicatorId": "bn-gsr-mrch-cd",
    "rank": 164,
    "decimal": 0
  },
  {
    "countryId": "jo",
    "date": 2023,
    "value": -10365633802.8169,
    "indicatorId": "bn-gsr-mrch-cd",
    "rank": 165,
    "decimal": 0
  },
  {
    "countryId": "pa",
    "date": 2023,
    "value": -11085272573.35,
    "indicatorId": "bn-gsr-mrch-cd",
    "rank": 166,
    "decimal": 0
  },
  {
    "countryId": "et",
    "date": 2023,
    "value": -11848615110.5667,
    "indicatorId": "bn-gsr-mrch-cd",
    "rank": 167,
    "decimal": 0
  },
  {
    "countryId": "mo",
    "date": 2023,
    "value": -12113385420.1249,
    "indicatorId": "bn-gsr-mrch-cd",
    "rank": 168,
    "decimal": 0
  },
  {
    "countryId": "lb",
    "date": 2023,
    "value": -12838323957.2616,
    "indicatorId": "bn-gsr-mrch-cd",
    "rank": 169,
    "decimal": 0
  },
  {
    "countryId": "np",
    "date": 2024,
    "value": -13060693536.4077,
    "indicatorId": "bn-gsr-mrch-cd",
    "rank": 170,
    "decimal": 0
  },
  {
    "countryId": "gt",
    "date": 2023,
    "value": -14359132350,
    "indicatorId": "bn-gsr-mrch-cd",
    "rank": 171,
    "decimal": 0
  },
  {
    "countryId": "uz",
    "date": 2023,
    "value": -14858973274.1914,
    "indicatorId": "bn-gsr-mrch-cd",
    "rank": 172,
    "decimal": 0
  },
  {
    "countryId": "do",
    "date": 2023,
    "value": -15891200000,
    "indicatorId": "bn-gsr-mrch-cd",
    "rank": 173,
    "decimal": 0
  },
  {
    "countryId": "hk",
    "date": 2023,
    "value": -16117745730.5614,
    "indicatorId": "bn-gsr-mrch-cd",
    "rank": 174,
    "decimal": 0
  },
  {
    "countryId": "hr",
    "date": 2023,
    "value": -18951054156.9572,
    "indicatorId": "bn-gsr-mrch-cd",
    "rank": 175,
    "decimal": 0
  },
  {
    "countryId": "bd",
    "date": 2023,
    "value": -22692111206.3858,
    "indicatorId": "bn-gsr-mrch-cd",
    "rank": 176,
    "decimal": 0
  },
  {
    "countryId": "pk",
    "date": 2024,
    "value": -23484000000,
    "indicatorId": "bn-gsr-mrch-cd",
    "rank": 177,
    "decimal": 0
  },
  {
    "countryId": "ma",
    "date": 2023,
    "value": -25112417349.7984,
    "indicatorId": "bn-gsr-mrch-cd",
    "rank": 178,
    "decimal": 0
  },
  {
    "countryId": "eg",
    "date": 2023,
    "value": -25690637500,
    "indicatorId": "bn-gsr-mrch-cd",
    "rank": 179,
    "decimal": 0
  },
  {
    "countryId": "il",
    "date": 2024,
    "value": -26322900000,
    "indicatorId": "bn-gsr-mrch-cd",
    "rank": 180,
    "decimal": 0
  },
  {
    "countryId": "pt",
    "date": 2024,
    "value": -27332830759.5965,
    "indicatorId": "bn-gsr-mrch-cd",
    "rank": 181,
    "decimal": 0
  },
  {
    "countryId": "ua",
    "date": 2023,
    "value": -29135000000,
    "indicatorId": "bn-gsr-mrch-cd",
    "rank": 182,
    "decimal": 0
  },
  {
    "countryId": "ro",
    "date": 2023,
    "value": -31328186562.8399,
    "indicatorId": "bn-gsr-mrch-cd",
    "rank": 183,
    "decimal": 0
  },
  {
    "countryId": "gr",
    "date": 2023,
    "value": -35712914861.3777,
    "indicatorId": "bn-gsr-mrch-cd",
    "rank": 184,
    "decimal": 0
  },
  {
    "countryId": "es",
    "date": 2023,
    "value": -37500376165.2326,
    "indicatorId": "bn-gsr-mrch-cd",
    "rank": 185,
    "decimal": 0
  },
  {
    "countryId": "jp",
    "date": 2023,
    "value": -47856336605.5052,
    "indicatorId": "bn-gsr-mrch-cd",
    "rank": 186,
    "decimal": 0
  },
  {
    "countryId": "tr",
    "date": 2024,
    "value": -56258000000,
    "indicatorId": "bn-gsr-mrch-cd",
    "rank": 187,
    "decimal": 0
  },
  {
    "countryId": "ph",
    "date": 2024,
    "value": -68744346164.5419,
    "indicatorId": "bn-gsr-mrch-cd",
    "rank": 188,
    "decimal": 0
  },
  {
    "countryId": "fr",
    "date": 2023,
    "value": -82338005121.2914,
    "indicatorId": "bn-gsr-mrch-cd",
    "rank": 189,
    "decimal": 0
  },
  {
    "countryId": "gb",
    "date": 2023,
    "value": -230390520894.042,
    "indicatorId": "bn-gsr-mrch-cd",
    "rank": 190,
    "decimal": 0
  },
  {
    "countryId": "in",
    "date": 2023,
    "value": -245472722918.639,
    "indicatorId": "bn-gsr-mrch-cd",
    "rank": 191,
    "decimal": 0
  },
  {
    "countryId": "us",
    "date": 2023,
    "value": -1063289000000,
    "indicatorId": "bn-gsr-mrch-cd",
    "rank": 192,
    "decimal": 0
  }
]