[
  {
    "countryId": "lu",
    "date": 2024,
    "value": 150772.358842278,
    "indicatorId": "ny-gdp-pcap-pp-cd",
    "rank": 1,
    "decimal": 1
  },
  {
    "countryId": "sg",
    "date": 2024,
    "value": 150689.301625826,
    "indicatorId": "ny-gdp-pcap-pp-cd",
    "rank": 2,
    "decimal": 1
  },
  {
    "countryId": "ie",
    "date": 2024,
    "value": 131175.106854149,
    "indicatorId": "ny-gdp-pcap-pp-cd",
    "rank": 3,
    "decimal": 1
  },
  {
    "countryId": "qa",
    "date": 2024,
    "value": 126110.108801588,
    "indicatorId": "ny-gdp-pcap-pp-cd",
    "rank": 4,
    "decimal": 1
  },
  {
    "countryId": "no",
    "date": 2024,
    "value": 101031.587516818,
    "indicatorId": "ny-gdp-pcap-pp-cd",
    "rank": 5,
    "decimal": 1
  },
  {
    "countryId": "ch",
    "date": 2024,
    "value": 93818.7074809256,
    "indicatorId": "ny-gdp-pcap-pp-cd",
    "rank": 6,
    "decimal": 1
  },
  {
    "countryId": "bn",
    "date": 2024,
    "value": 90007.077485547,
    "indicatorId": "ny-gdp-pcap-pp-cd",
    "rank": 7,
    "decimal": 1
  },
  {
    "countryId": "us",
    "date": 2024,
    "value": 85809.9003846359,
    "indicatorId": "ny-gdp-pcap-pp-cd",
    "rank": 8,
    "decimal": 1
  },
  {
    "countryId": "nl",
    "date": 2024,
    "value": 84218.4586435096,
    "indicatorId": "ny-gdp-pcap-pp-cd",
    "rank": 9,
    "decimal": 1
  },
  {
    "countryId": "gy",
    "date": 2024,
    "value": 79905.7442521973,
    "indicatorId": "ny-gdp-pcap-pp-cd",
    "rank": 10,
    "decimal": 1
  },
  {
    "countryId": "dk",
    "date": 2024,
    "value": 79514.2854383058,
    "indicatorId": "ny-gdp-pcap-pp-cd",
    "rank": 11,
    "decimal": 1
  },
  {
    "countryId": "is",
    "date": 2024,
    "value": 78258.759250789,
    "indicatorId": "ny-gdp-pcap-pp-cd",
    "rank": 12,
    "decimal": 1
  },
  {
    "countryId": "ae",
    "date": 2024,
    "value": 77958.8954093036,
    "indicatorId": "ny-gdp-pcap-pp-cd",
    "rank": 13,
    "decimal": 1
  },
  {
    "countryId": "sm",
    "date": 2022,
    "value": 75941.4899090162,
    "indicatorId": "ny-gdp-pcap-pp-cd",
    "rank": 14,
    "decimal": 1
  },
  {
    "countryId": "ad",
    "date": 2024,
    "value": 74939.4746038578,
    "indicatorId": "ny-gdp-pcap-pp-cd",
    "rank": 15,
    "decimal": 1
  },
  {
    "countryId": "de",
    "date": 2024,
    "value": 72300.1205050011,
    "indicatorId": "ny-gdp-pcap-pp-cd",
    "rank": 16,
    "decimal": 1
  },
  {
    "countryId": "be",
    "date": 2024,
    "value": 72126.0028888089,
    "indicatorId": "ny-gdp-pcap-pp-cd",
    "rank": 17,
    "decimal": 1
  },
  {
    "countryId": "at",
    "date": 2024,
    "value": 71617.9017496321,
    "indicatorId": "ny-gdp-pcap-pp-cd",
    "rank": 18,
    "decimal": 1
  },
  {
    "countryId": "sa",
    "date": 2024,
    "value": 71243.4311791406,
    "indicatorId": "ny-gdp-pcap-pp-cd",
    "rank": 19,
    "decimal": 1
  },
  {
    "countryId": "au",
    "date": 2024,
    "value": 71193.2158509788,
    "indicatorId": "ny-gdp-pcap-pp-cd",
    "rank": 20,
    "decimal": 1
  },
  {
    "countryId": "se",
    "date": 2024,
    "value": 71030.4601718093,
    "indicatorId": "ny-gdp-pcap-pp-cd",
    "rank": 21,
    "decimal": 1
  },
  {
    "countryId": "mt",
    "date": 2024,
    "value": 67364.1825074247,
    "indicatorId": "ny-gdp-pcap-pp-cd",
    "rank": 22,
    "decimal": 1
  },
  {
    "countryId": "bh",
    "date": 2024,
    "value": 67210.9890947485,
    "indicatorId": "ny-gdp-pcap-pp-cd",
    "rank": 23,
    "decimal": 1
  },
  {
    "countryId": "ca",
    "date": 2024,
    "value": 65463.0990993361,
    "indicatorId": "ny-gdp-pcap-pp-cd",
    "rank": 24,
    "decimal": 1
  },
  {
    "countryId": "fi",
    "date": 2024,
    "value": 64091.2251829548,
    "indicatorId": "ny-gdp-pcap-pp-cd",
    "rank": 25,
    "decimal": 1
  },
  {
    "countryId": "fr",
    "date": 2024,
    "value": 61321.691319446,
    "indicatorId": "ny-gdp-pcap-pp-cd",
    "rank": 26,
    "decimal": 1
  },
  {
    "countryId": "cy",
    "date": 2024,
    "value": 61239.66015625,
    "indicatorId": "ny-gdp-pcap-pp-cd",
    "rank": 27,
    "decimal": 1
  },
  {
    "countryId": "it",
    "date": 2024,
    "value": 60846.9830270279,
    "indicatorId": "ny-gdp-pcap-pp-cd",
    "rank": 28,
    "decimal": 1
  },
  {
    "countryId": "gb",
    "date": 2024,
    "value": 60620.3807747583,
    "indicatorId": "ny-gdp-pcap-pp-cd",
    "rank": 29,
    "decimal": 1
  },
  {
    "countryId": "es",
    "date": 2024,
    "value": 56926.2399029671,
    "indicatorId": "ny-gdp-pcap-pp-cd",
    "rank": 30,
    "decimal": 1
  },
  {
    "countryId": "cz",
    "date": 2024,
    "value": 56805.6467676779,
    "indicatorId": "ny-gdp-pcap-pp-cd",
    "rank": 31,
    "decimal": 1
  },
  {
    "countryId": "si",
    "date": 2024,
    "value": 56530.6296825064,
    "indicatorId": "ny-gdp-pcap-pp-cd",
    "rank": 32,
    "decimal": 1
  },
  {
    "countryId": "il",
    "date": 2024,
    "value": 55690.7391030986,
    "indicatorId": "ny-gdp-pcap-pp-cd",
    "rank": 33,
    "decimal": 1
  },
  {
    "countryId": "nz",
    "date": 2024,
    "value": 55093.5360762134,
    "indicatorId": "ny-gdp-pcap-pp-cd",
    "rank": 34,
    "decimal": 1
  },
  {
    "countryId": "lt",
    "date": 2024,
    "value": 54413.9640682813,
    "indicatorId": "ny-gdp-pcap-pp-cd",
    "rank": 35,
    "decimal": 1
  },
  {
    "countryId": "kr",
    "date": 2023,
    "value": 52203.9685660494,
    "indicatorId": "ny-gdp-pcap-pp-cd",
    "rank": 36,
    "decimal": 1
  },
  {
    "countryId": "jp",
    "date": 2024,
    "value": 51685.038752551,
    "indicatorId": "ny-gdp-pcap-pp-cd",
    "rank": 37,
    "decimal": 1
  },
  {
    "countryId": "kw",
    "date": 2024,
    "value": 51635.9598107224,
    "indicatorId": "ny-gdp-pcap-pp-cd",
    "rank": 38,
    "decimal": 1
  },
  {
    "countryId": "pt",
    "date": 2024,
    "value": 50616.5930893707,
    "indicatorId": "ny-gdp-pcap-pp-cd",
    "rank": 39,
    "decimal": 1
  },
  {
    "countryId": "pl",
    "date": 2024,
    "value": 50378.0641849255,
    "indicatorId": "ny-gdp-pcap-pp-cd",
    "rank": 40,
    "decimal": 1
  },
  {
    "countryId": "ee",
    "date": 2024,
    "value": 49333.8067758296,
    "indicatorId": "ny-gdp-pcap-pp-cd",
    "rank": 41,
    "decimal": 1
  },
  {
    "countryId": "ro",
    "date": 2024,
    "value": 48712.173062205,
    "indicatorId": "ny-gdp-pcap-pp-cd",
    "rank": 42,
    "decimal": 1
  },
  {
    "countryId": "hr",
    "date": 2024,
    "value": 48575.2136083001,
    "indicatorId": "ny-gdp-pcap-pp-cd",
    "rank": 43,
    "decimal": 1
  },
  {
    "countryId": "hu",
    "date": 2024,
    "value": 47635.8955299223,
    "indicatorId": "ny-gdp-pcap-pp-cd",
    "rank": 44,
    "decimal": 1
  },
  {
    "countryId": "ru",
    "date": 2024,
    "value": 47404.96484375,
    "indicatorId": "ny-gdp-pcap-pp-cd",
    "rank": 45,
    "decimal": 1
  },
  {
    "countryId": "sk",
    "date": 2024,
    "value": 47180.8487662884,
    "indicatorId": "ny-gdp-pcap-pp-cd",
    "rank": 46,
    "decimal": 1
  },
  {
    "countryId": "gr",
    "date": 2024,
    "value": 44074.2956697377,
    "indicatorId": "ny-gdp-pcap-pp-cd",
    "rank": 47,
    "decimal": 1
  },
  {
    "countryId": "tr",
    "date": 2024,
    "value": 43932.0822203006,
    "indicatorId": "ny-gdp-pcap-pp-cd",
    "rank": 48,
    "decimal": 1
  },
  {
    "countryId": "lv",
    "date": 2024,
    "value": 43866.9592690499,
    "indicatorId": "ny-gdp-pcap-pp-cd",
    "rank": 49,
    "decimal": 1
  },
  {
    "countryId": "om",
    "date": 2024,
    "value": 41664.1794999015,
    "indicatorId": "ny-gdp-pcap-pp-cd",
    "rank": 50,
    "decimal": 1
  },
  {
    "countryId": "pa",
    "date": 2024,
    "value": 41404.7624346218,
    "indicatorId": "ny-gdp-pcap-pp-cd",
    "rank": 51,
    "decimal": 1
  },
  {
    "countryId": "bs",
    "date": 2024,
    "value": 41197.9183829907,
    "indicatorId": "ny-gdp-pcap-pp-cd",
    "rank": 52,
    "decimal": 1
  },
  {
    "countryId": "bg",
    "date": 2024,
    "value": 41086.1194132913,
    "indicatorId": "ny-gdp-pcap-pp-cd",
    "rank": 53,
    "decimal": 1
  },
  {
    "countryId": "kz",
    "date": 2024,
    "value": 40813.0442804706,
    "indicatorId": "ny-gdp-pcap-pp-cd",
    "rank": 54,
    "decimal": 1
  },
  {
    "countryId": "my",
    "date": 2024,
    "value": 38728.9430329388,
    "indicatorId": "ny-gdp-pcap-pp-cd",
    "rank": 55,
    "decimal": 1
  },
  {
    "countryId": "uy",
    "date": 2024,
    "value": 36417.874162496,
    "indicatorId": "ny-gdp-pcap-pp-cd",
    "rank": 56,
    "decimal": 1
  },
  {
    "countryId": "tt",
    "date": 2024,
    "value": 36021.1259580231,
    "indicatorId": "ny-gdp-pcap-pp-cd",
    "rank": 57,
    "decimal": 1
  },
  {
    "countryId": "kn",
    "date": 2024,
    "value": 35544.807538702,
    "indicatorId": "ny-gdp-pcap-pp-cd",
    "rank": 58,
    "decimal": 1
  },
  {
    "countryId": "cl",
    "date": 2024,
    "value": 34637.1168279143,
    "indicatorId": "ny-gdp-pcap-pp-cd",
    "rank": 59,
    "decimal": 1
  },
  {
    "countryId": "ag",
    "date": 2024,
    "value": 33602.3539957929,
    "indicatorId": "ny-gdp-pcap-pp-cd",
    "rank": 60,
    "decimal": 1
  },
  {
    "countryId": "me",
    "date": 2024,
    "value": 33379.6432555927,
    "indicatorId": "ny-gdp-pcap-pp-cd",
    "rank": 61,
    "decimal": 1
  },
  {
    "countryId": "sc",
    "date": 2024,
    "value": 33238.5800343754,
    "indicatorId": "ny-gdp-pcap-pp-cd",
    "rank": 62,
    "decimal": 1
  },
  {
    "countryId": "by",
    "date": 2024,
    "value": 33006.4166677827,
    "indicatorId": "ny-gdp-pcap-pp-cd",
    "rank": 63,
    "decimal": 1
  },
  {
    "countryId": "rs",
    "date": 2024,
    "value": 31867.2389617503,
    "indicatorId": "ny-gdp-pcap-pp-cd",
    "rank": 64,
    "decimal": 1
  },
  {
    "countryId": "mu",
    "date": 2024,
    "value": 31050.933959114,
    "indicatorId": "ny-gdp-pcap-pp-cd",
    "rank": 65,
    "decimal": 1
  },
  {
    "countryId": "ar",
    "date": 2024,
    "value": 30175.5359656699,
    "indicatorId": "ny-gdp-pcap-pp-cd",
    "rank": 66,
    "decimal": 1
  },
  {
    "countryId": "cr",
    "date": 2024,
    "value": 30062.849160468,
    "indicatorId": "ny-gdp-pcap-pp-cd",
    "rank": 67,
    "decimal": 1
  },
  {
    "countryId": "ge",
    "date": 2024,
    "value": 28417.7518669146,
    "indicatorId": "ny-gdp-pcap-pp-cd",
    "rank": 68,
    "decimal": 1
  },
  {
    "countryId": "lc",
    "date": 2024,
    "value": 27567.3280779839,
    "indicatorId": "ny-gdp-pcap-pp-cd",
    "rank": 69,
    "decimal": 1
  },
  {
    "countryId": "do",
    "date": 2024,
    "value": 27541.183570599,
    "indicatorId": "ny-gdp-pcap-pp-cd",
    "rank": 70,
    "decimal": 1
  },
  {
    "countryId": "cn",
    "date": 2024,
    "value": 27104.8702677463,
    "indicatorId": "ny-gdp-pcap-pp-cd",
    "rank": 71,
    "decimal": 1
  },
  {
    "countryId": "mk",
    "date": 2024,
    "value": 26587.0325872589,
    "indicatorId": "ny-gdp-pcap-pp-cd",
    "rank": 72,
    "decimal": 1
  },
  {
    "countryId": "mv",
    "date": 2024,
    "value": 26542.7065404295,
    "indicatorId": "ny-gdp-pcap-pp-cd",
    "rank": 73,
    "decimal": 1
  },
  {
    "countryId": "mx",
    "date": 2024,
    "value": 25688.0964960445,
    "indicatorId": "ny-gdp-pcap-pp-cd",
    "rank": 74,
    "decimal": 1
  },
  {
    "countryId": "az",
    "date": 2024,
    "value": 25088.9501767555,
    "indicatorId": "ny-gdp-pcap-pp-cd",
    "rank": 75,
    "decimal": 1
  },
  {
    "countryId": "th",
    "date": 2024,
    "value": 24708.2439372088,
    "indicatorId": "ny-gdp-pcap-pp-cd",
    "rank": 76,
    "decimal": 1
  },
  {
    "countryId": "al",
    "date": 2024,
    "value": 23487.9936251703,
    "indicatorId": "ny-gdp-pcap-pp-cd",
    "rank": 77,
    "decimal": 1
  },
  {
    "countryId": "am",
    "date": 2024,
    "value": 22823.1795255692,
    "indicatorId": "ny-gdp-pcap-pp-cd",
    "rank": 78,
    "decimal": 1
  },
  {
    "countryId": "bb",
    "date": 2024,
    "value": 22671.9466863479,
    "indicatorId": "ny-gdp-pcap-pp-cd",
    "rank": 79,
    "decimal": 1
  },
  {
    "countryId": "br",
    "date": 2024,
    "value": 22333.4116642585,
    "indicatorId": "ny-gdp-pcap-pp-cd",
    "rank": 80,
    "decimal": 1
  },
  {
    "countryId": "sr",
    "date": 2024,
    "value": 22066.7320723321,
    "indicatorId": "ny-gdp-pcap-pp-cd",
    "rank": 81,
    "decimal": 1
  },
  {
    "countryId": "ba",
    "date": 2024,
    "value": 21971.0503961563,
    "indicatorId": "ny-gdp-pcap-pp-cd",
    "rank": 82,
    "decimal": 1
  },
  {
    "countryId": "ga",
    "date": 2024,
    "value": 21509.5227883553,
    "indicatorId": "ny-gdp-pcap-pp-cd",
    "rank": 83,
    "decimal": 1
  },
  {
    "countryId": "co",
    "date": 2024,
    "value": 21494.6002713853,
    "indicatorId": "ny-gdp-pcap-pp-cd",
    "rank": 84,
    "decimal": 1
  },
  {
    "countryId": "dm",
    "date": 2024,
    "value": 21300.6848698089,
    "indicatorId": "ny-gdp-pcap-pp-cd",
    "rank": 85,
    "decimal": 1
  },
  {
    "countryId": "vc",
    "date": 2024,
    "value": 21272.0800673662,
    "indicatorId": "ny-gdp-pcap-pp-cd",
    "rank": 86,
    "decimal": 1
  },
  {
    "countryId": "bw",
    "date": 2024,
    "value": 20538.1320160386,
    "indicatorId": "ny-gdp-pcap-pp-cd",
    "rank": 87,
    "decimal": 1
  },
  {
    "countryId": "tm",
    "date": 2024,
    "value": 20407.8009519632,
    "indicatorId": "ny-gdp-pcap-pp-cd",
    "rank": 88,
    "decimal": 1
  },
  {
    "countryId": "gd",
    "date": 2024,
    "value": 20167.1993754495,
    "indicatorId": "ny-gdp-pcap-pp-cd",
    "rank": 89,
    "decimal": 1
  },
  {
    "countryId": "mn",
    "date": 2024,
    "value": 19097.7314186395,
    "indicatorId": "ny-gdp-pcap-pp-cd",
    "rank": 90,
    "decimal": 1
  },
  {
    "countryId": "eg",
    "date": 2024,
    "value": 19094.1449444111,
    "indicatorId": "ny-gdp-pcap-pp-cd",
    "rank": 91,
    "decimal": 1
  },
  {
    "countryId": "md",
    "date": 2024,
    "value": 18716.5133942394,
    "indicatorId": "ny-gdp-pcap-pp-cd",
    "rank": 92,
    "decimal": 1
  },
  {
    "countryId": "ua",
    "date": 2024,
    "value": 18550.462890625,
    "indicatorId": "ny-gdp-pcap-pp-cd",
    "rank": 93,
    "decimal": 1
  },
  {
    "countryId": "py",
    "date": 2024,
    "value": 18523.6810153005,
    "indicatorId": "ny-gdp-pcap-pp-cd",
    "rank": 94,
    "decimal": 1
  },
  {
    "countryId": "ir",
    "date": 2024,
    "value": 18441.5577521605,
    "indicatorId": "ny-gdp-pcap-pp-cd",
    "rank": 95,
    "decimal": 1
  },
  {
    "countryId": "pe",
    "date": 2024,
    "value": 17802.4182498972,
    "indicatorId": "ny-gdp-pcap-pp-cd",
    "rank": 96,
    "decimal": 1
  },
  {
    "countryId": "gq",
    "date": 2024,
    "value": 17566.7600284073,
    "indicatorId": "ny-gdp-pcap-pp-cd",
    "rank": 97,
    "decimal": 1
  },
  {
    "countryId": "dz",
    "date": 2024,
    "value": 17552.7742475631,
    "indicatorId": "ny-gdp-pcap-pp-cd",
    "rank": 98,
    "decimal": 1
  },
  {
    "countryId": "pw",
    "date": 2023,
    "value": 17531.6926506844,
    "indicatorId": "ny-gdp-pcap-pp-cd",
    "rank": 99,
    "decimal": 1
  },
  {
    "countryId": "id",
    "date": 2024,
    "value": 16448.2755179559,
    "indicatorId": "ny-gdp-pcap-pp-cd",
    "rank": 100,
    "decimal": 1
  },
  {
    "countryId": "vn",
    "date": 2024,
    "value": 16385.5065565458,
    "indicatorId": "ny-gdp-pcap-pp-cd",
    "rank": 101,
    "decimal": 1
  },
  {
    "countryId": "bt",
    "date": 2023,
    "value": 16253.9629503074,
    "indicatorId": "ny-gdp-pcap-pp-cd",
    "rank": 102,
    "decimal": 1
  },
  {
    "countryId": "fj",
    "date": 2024,
    "value": 16032.257408619,
    "indicatorId": "ny-gdp-pcap-pp-cd",
    "rank": 103,
    "decimal": 1
  },
  {
    "countryId": "ec",
    "date": 2024,
    "value": 15840.2668567412,
    "indicatorId": "ny-gdp-pcap-pp-cd",
    "rank": 104,
    "decimal": 1
  },
  {
    "countryId": "lk",
    "date": 2024,
    "value": 15632.5924849848,
    "indicatorId": "ny-gdp-pcap-pp-cd",
    "rank": 105,
    "decimal": 1
  },
  {
    "countryId": "za",
    "date": 2024,
    "value": 15457.4891449518,
    "indicatorId": "ny-gdp-pcap-pp-cd",
    "rank": 106,
    "decimal": 1
  },
  {
    "countryId": "bz",
    "date": 2024,
    "value": 15092.7808546669,
    "indicatorId": "ny-gdp-pcap-pp-cd",
    "rank": 107,
    "decimal": 1
  },
  {
    "countryId": "iq",
    "date": 2024,
    "value": 14464.3186928173,
    "indicatorId": "ny-gdp-pcap-pp-cd",
    "rank": 108,
    "decimal": 1
  },
  {
    "countryId": "tn",
    "date": 2024,
    "value": 14451.2544977748,
    "indicatorId": "ny-gdp-pcap-pp-cd",
    "rank": 109,
    "decimal": 1
  },
  {
    "countryId": "gt",
    "date": 2024,
    "value": 14368.6601241885,
    "indicatorId": "ny-gdp-pcap-pp-cd",
    "rank": 110,
    "decimal": 1
  },
  {
    "countryId": "nr",
    "date": 2024,
    "value": 14326.8023151623,
    "indicatorId": "ny-gdp-pcap-pp-cd",
    "rank": 111,
    "decimal": 1
  },
  {
    "countryId": "ly",
    "date": 2024,
    "value": 13953.7980283318,
    "indicatorId": "ny-gdp-pcap-pp-cd",
    "rank": 112,
    "decimal": 1
  },
  {
    "countryId": "sv",
    "date": 2024,
    "value": 13264.027090968,
    "indicatorId": "ny-gdp-pcap-pp-cd",
    "rank": 113,
    "decimal": 1
  },
  {
    "countryId": "lb",
    "date": 2023,
    "value": 12574.8329116403,
    "indicatorId": "ny-gdp-pcap-pp-cd",
    "rank": 114,
    "decimal": 1
  },
  {
    "countryId": "uz",
    "date": 2024,
    "value": 11878.5528706848,
    "indicatorId": "ny-gdp-pcap-pp-cd",
    "rank": 115,
    "decimal": 1
  },
  {
    "countryId": "ph",
    "date": 2024,
    "value": 11794.1375488492,
    "indicatorId": "ny-gdp-pcap-pp-cd",
    "rank": 116,
    "decimal": 1
  },
  {
    "countryId": "sz",
    "date": 2024,
    "value": 11784.2800637308,
    "indicatorId": "ny-gdp-pcap-pp-cd",
    "rank": 117,
    "decimal": 1
  },
  {
    "countryId": "na",
    "date": 2024,
    "value": 11686.6020624775,
    "indicatorId": "ny-gdp-pcap-pp-cd",
    "rank": 118,
    "decimal": 1
  },
  {
    "countryId": "jm",
    "date": 2024,
    "value": 11662.3446837367,
    "indicatorId": "ny-gdp-pcap-pp-cd",
    "rank": 119,
    "decimal": 1
  },
  {
    "countryId": "cv",
    "date": 2024,
    "value": 11261.7706486365,
    "indicatorId": "ny-gdp-pcap-pp-cd",
    "rank": 120,
    "decimal": 1
  },
  {
    "countryId": "bo",
    "date": 2024,
    "value": 11189.8055097036,
    "indicatorId": "ny-gdp-pcap-pp-cd",
    "rank": 121,
    "decimal": 1
  },
  {
    "countryId": "in",
    "date": 2024,
    "value": 11158.8809230756,
    "indicatorId": "ny-gdp-pcap-pp-cd",
    "rank": 122,
    "decimal": 1
  },
  {
    "countryId": "jo",
    "date": 2024,
    "value": 10821.4909765317,
    "indicatorId": "ny-gdp-pcap-pp-cd",
    "rank": 123,
    "decimal": 1
  },
  {
    "countryId": "ma",
    "date": 2024,
    "value": 10305.0546875,
    "indicatorId": "ny-gdp-pcap-pp-cd",
    "rank": 124,
    "decimal": 1
  },
  {
    "countryId": "la",
    "date": 2024,
    "value": 9787.85098404365,
    "indicatorId": "ny-gdp-pcap-pp-cd",
    "rank": 125,
    "decimal": 1
  },
  {
    "countryId": "bd",
    "date": 2024,
    "value": 9646.76984383255,
    "indicatorId": "ny-gdp-pcap-pp-cd",
    "rank": 126,
    "decimal": 1
  },
  {
    "countryId": "ni",
    "date": 2024,
    "value": 8708.79983051626,
    "indicatorId": "ny-gdp-pcap-pp-cd",
    "rank": 127,
    "decimal": 1
  },
  {
    "countryId": "ao",
    "date": 2024,
    "value": 8347.95279117055,
    "indicatorId": "ny-gdp-pcap-pp-cd",
    "rank": 128,
    "decimal": 1
  },
  {
    "countryId": "mh",
    "date": 2024,
    "value": 8198.12563302958,
    "indicatorId": "ny-gdp-pcap-pp-cd",
    "rank": 129,
    "decimal": 1
  },
  {
    "countryId": "gh",
    "date": 2024,
    "value": 8027.16842346122,
    "indicatorId": "ny-gdp-pcap-pp-cd",
    "rank": 130,
    "decimal": 1
  },
  {
    "countryId": "kg",
    "date": 2024,
    "value": 8009.40919445692,
    "indicatorId": "ny-gdp-pcap-pp-cd",
    "rank": 131,
    "decimal": 1
  },
  {
    "countryId": "kh",
    "date": 2024,
    "value": 7969.93361077408,
    "indicatorId": "ny-gdp-pcap-pp-cd",
    "rank": 132,
    "decimal": 1
  },
  {
    "countryId": "to",
    "date": 2023,
    "value": 7852.76498057614,
    "indicatorId": "ny-gdp-pcap-pp-cd",
    "rank": 133,
    "decimal": 1
  },
  {
    "countryId": "ws",
    "date": 2024,
    "value": 7837.29243441426,
    "indicatorId": "ny-gdp-pcap-pp-cd",
    "rank": 134,
    "decimal": 1
  },
  {
    "countryId": "dj",
    "date": 2024,
    "value": 7776.22613645201,
    "indicatorId": "ny-gdp-pcap-pp-cd",
    "rank": 135,
    "decimal": 1
  },
  {
    "countryId": "ci",
    "date": 2024,
    "value": 7653.45033756027,
    "indicatorId": "ny-gdp-pcap-pp-cd",
    "rank": 136,
    "decimal": 1
  },
  {
    "countryId": "hn",
    "date": 2024,
    "value": 7486.01869616445,
    "indicatorId": "ny-gdp-pcap-pp-cd",
    "rank": 137,
    "decimal": 1
  },
  {
    "countryId": "mr",
    "date": 2024,
    "value": 7271.34040477207,
    "indicatorId": "ny-gdp-pcap-pp-cd",
    "rank": 138,
    "decimal": 1
  },
  {
    "countryId": "cg",
    "date": 2024,
    "value": 7026.36202432036,
    "indicatorId": "ny-gdp-pcap-pp-cd",
    "rank": 139,
    "decimal": 1
  },
  {
    "countryId": "ke",
    "date": 2024,
    "value": 6619.35857448994,
    "indicatorId": "ny-gdp-pcap-pp-cd",
    "rank": 140,
    "decimal": 1
  },
  {
    "countryId": "ng",
    "date": 2024,
    "value": 6439.81292158502,
    "indicatorId": "ny-gdp-pcap-pp-cd",
    "rank": 141,
    "decimal": 1
  },
  {
    "countryId": "pk",
    "date": 2024,
    "value": 6286.9799268998,
    "indicatorId": "ny-gdp-pcap-pp-cd",
    "rank": 142,
    "decimal": 1
  },
  {
    "countryId": "st",
    "date": 2024,
    "value": 6229.50833298788,
    "indicatorId": "ny-gdp-pcap-pp-cd",
    "rank": 143,
    "decimal": 1
  },
  {
    "countryId": "tv",
    "date": 2023,
    "value": 6151.01047041608,
    "indicatorId": "ny-gdp-pcap-pp-cd",
    "rank": 144,
    "decimal": 1
  },
  {
    "countryId": "mm",
    "date": 2024,
    "value": 5997.46516323715,
    "indicatorId": "ny-gdp-pcap-pp-cd",
    "rank": 145,
    "decimal": 1
  },
  {
    "countryId": "np",
    "date": 2024,
    "value": 5736.62134332704,
    "indicatorId": "ny-gdp-pcap-pp-cd",
    "rank": 146,
    "decimal": 1
  },
  {
    "countryId": "cm",
    "date": 2024,
    "value": 5591.49639781706,
    "indicatorId": "ny-gdp-pcap-pp-cd",
    "rank": 147,
    "decimal": 1
  },
  {
    "countryId": "tj",
    "date": 2024,
    "value": 5405.98011619139,
    "indicatorId": "ny-gdp-pcap-pp-cd",
    "rank": 148,
    "decimal": 1
  },
  {
    "countryId": "sn",
    "date": 2024,
    "value": 5110.39969800342,
    "indicatorId": "ny-gdp-pcap-pp-cd",
    "rank": 149,
    "decimal": 1
  },
  {
    "countryId": "pg",
    "date": 2024,
    "value": 4888.55483136173,
    "indicatorId": "ny-gdp-pcap-pp-cd",
    "rank": 150,
    "decimal": 1
  },
  {
    "countryId": "tl",
    "date": 2024,
    "value": 4758.39202005466,
    "indicatorId": "ny-gdp-pcap-pp-cd",
    "rank": 151,
    "decimal": 1
  },
  {
    "countryId": "sy",
    "date": 2023,
    "value": 4650.06687798544,
    "indicatorId": "ny-gdp-pcap-pp-cd",
    "rank": 152,
    "decimal": 1
  },
  {
    "countryId": "gn",
    "date": 2024,
    "value": 4579.10187311541,
    "indicatorId": "ny-gdp-pcap-pp-cd",
    "rank": 153,
    "decimal": 1
  },
  {
    "countryId": "bj",
    "date": 2024,
    "value": 4434.5642184028,
    "indicatorId": "ny-gdp-pcap-pp-cd",
    "rank": 154,
    "decimal": 1
  },
  {
    "countryId": "fm",
    "date": 2024,
    "value": 4346.21932945529,
    "indicatorId": "ny-gdp-pcap-pp-cd",
    "rank": 155,
    "decimal": 1
  },
  {
    "countryId": "zm",
    "date": 2024,
    "value": 4223.95020752457,
    "indicatorId": "ny-gdp-pcap-pp-cd",
    "rank": 156,
    "decimal": 1
  },
  {
    "countryId": "tz",
    "date": 2024,
    "value": 4220.79638671875,
    "indicatorId": "ny-gdp-pcap-pp-cd",
    "rank": 157,
    "decimal": 1
  },
  {
    "countryId": "km",
    "date": 2024,
    "value": 4055.12633434507,
    "indicatorId": "ny-gdp-pcap-pp-cd",
    "rank": 158,
    "decimal": 1
  },
  {
    "countryId": "zw",
    "date": 2024,
    "value": 3921.69795648277,
    "indicatorId": "ny-gdp-pcap-pp-cd",
    "rank": 159,
    "decimal": 1
  },
  {
    "countryId": "rw",
    "date": 2024,
    "value": 3710.86040434596,
    "indicatorId": "ny-gdp-pcap-pp-cd",
    "rank": 160,
    "decimal": 1
  },
  {
    "countryId": "ki",
    "date": 2024,
    "value": 3702.32600979985,
    "indicatorId": "ny-gdp-pcap-pp-cd",
    "rank": 161,
    "decimal": 1
  },
  {
    "countryId": "vu",
    "date": 2024,
    "value": 3602.40727009487,
    "indicatorId": "ny-gdp-pcap-pp-cd",
    "rank": 162,
    "decimal": 1
  },
  {
    "countryId": "sl",
    "date": 2024,
    "value": 3515.56271258888,
    "indicatorId": "ny-gdp-pcap-pp-cd",
    "rank": 163,
    "decimal": 1
  },
  {
    "countryId": "gm",
    "date": 2024,
    "value": 3445.25159248185,
    "indicatorId": "ny-gdp-pcap-pp-cd",
    "rank": 164,
    "decimal": 1
  },
  {
    "countryId": "ml",
    "date": 2024,
    "value": 3308.66948870441,
    "indicatorId": "ny-gdp-pcap-pp-cd",
    "rank": 165,
    "decimal": 1
  },
  {
    "countryId": "et",
    "date": 2024,
    "value": 3278.48967257937,
    "indicatorId": "ny-gdp-pcap-pp-cd",
    "rank": 166,
    "decimal": 1
  },
  {
    "countryId": "ug",
    "date": 2024,
    "value": 3275.7631600887,
    "indicatorId": "ny-gdp-pcap-pp-cd",
    "rank": 167,
    "decimal": 1
  },
  {
    "countryId": "tg",
    "date": 2024,
    "value": 3239.09143737535,
    "indicatorId": "ny-gdp-pcap-pp-cd",
    "rank": 168,
    "decimal": 1
  },
  {
    "countryId": "ht",
    "date": 2024,
    "value": 3183.45909033404,
    "indicatorId": "ny-gdp-pcap-pp-cd",
    "rank": 169,
    "decimal": 1
  },
  {
    "countryId": "gw",
    "date": 2024,
    "value": 3052.69113655728,
    "indicatorId": "ny-gdp-pcap-pp-cd",
    "rank": 170,
    "decimal": 1
  },
  {
    "countryId": "ls",
    "date": 2024,
    "value": 2998.47039504253,
    "indicatorId": "ny-gdp-pcap-pp-cd",
    "rank": 171,
    "decimal": 1
  },
  {
    "countryId": "td",
    "date": 2024,
    "value": 2961.9319239201,
    "indicatorId": "ny-gdp-pcap-pp-cd",
    "rank": 172,
    "decimal": 1
  },
  {
    "countryId": "bf",
    "date": 2024,
    "value": 2896.18741593759,
    "indicatorId": "ny-gdp-pcap-pp-cd",
    "rank": 173,
    "decimal": 1
  },
  {
    "countryId": "sb",
    "date": 2024,
    "value": 2872.47876193859,
    "indicatorId": "ny-gdp-pcap-pp-cd",
    "rank": 174,
    "decimal": 1
  },
  {
    "countryId": "af",
    "date": 2023,
    "value": 2201.72290691677,
    "indicatorId": "ny-gdp-pcap-pp-cd",
    "rank": 175,
    "decimal": 1
  },
  {
    "countryId": "sd",
    "date": 2024,
    "value": 2127.400390625,
    "indicatorId": "ny-gdp-pcap-pp-cd",
    "rank": 176,
    "decimal": 1
  },
  {
    "countryId": "ne",
    "date": 2024,
    "value": 2015.02282076047,
    "indicatorId": "ny-gdp-pcap-pp-cd",
    "rank": 177,
    "decimal": 1
  },
  {
    "countryId": "lr",
    "date": 2024,
    "value": 1884.91314291116,
    "indicatorId": "ny-gdp-pcap-pp-cd",
    "rank": 178,
    "decimal": 1
  },
  {
    "countryId": "mg",
    "date": 2024,
    "value": 1883.53743113319,
    "indicatorId": "ny-gdp-pcap-pp-cd",
    "rank": 179,
    "decimal": 1
  },
  {
    "countryId": "mw",
    "date": 2024,
    "value": 1859.44796067768,
    "indicatorId": "ny-gdp-pcap-pp-cd",
    "rank": 180,
    "decimal": 1
  },
  {
    "countryId": "cd",
    "date": 2024,
    "value": 1709.73207724172,
    "indicatorId": "ny-gdp-pcap-pp-cd",
    "rank": 181,
    "decimal": 1
  },
  {
    "countryId": "mz",
    "date": 2024,
    "value": 1699.70503405145,
    "indicatorId": "ny-gdp-pcap-pp-cd",
    "rank": 182,
    "decimal": 1
  },
  {
    "countryId": "so",
    "date": 2024,
    "value": 1600.76362114264,
    "indicatorId": "ny-gdp-pcap-pp-cd",
    "rank": 183,
    "decimal": 1
  },
  {
    "countryId": "cf",
    "date": 2024,
    "value": 1263.59554279079,
    "indicatorId": "ny-gdp-pcap-pp-cd",
    "rank": 184,
    "decimal": 1
  },
  {
    "countryId": "ss",
    "date": 2015,
    "value": 1154.88686304107,
    "indicatorId": "ny-gdp-pcap-pp-cd",
    "rank": 185,
    "decimal": 1
  },
  {
    "countryId": "bi",
    "date": 2024,
    "value": 949.834613118208,
    "indicatorId": "ny-gdp-pcap-pp-cd",
    "rank": 186,
    "decimal": 1
  }
]