[
  {
    "countryId": "ls",
    "date": 2023,
    "value": 38.5196302268772,
    "indicatorId": "sl-ind-empl-fe-zs",
    "rank": 1,
    "decimal": 0
  },
  {
    "countryId": "to",
    "date": 2023,
    "value": 36.7632433865942,
    "indicatorId": "sl-ind-empl-fe-zs",
    "rank": 2,
    "decimal": 0
  },
  {
    "countryId": "af",
    "date": 2023,
    "value": 33.8587111379347,
    "indicatorId": "sl-ind-empl-fe-zs",
    "rank": 3,
    "decimal": 0
  },
  {
    "countryId": "tn",
    "date": 2023,
    "value": 32.3324950753587,
    "indicatorId": "sl-ind-empl-fe-zs",
    "rank": 4,
    "decimal": 0
  },
  {
    "countryId": "cn",
    "date": 2023,
    "value": 28.2726196946588,
    "indicatorId": "sl-ind-empl-fe-zs",
    "rank": 5,
    "decimal": 0
  },
  {
    "countryId": "vn",
    "date": 2023,
    "value": 27.2958306394278,
    "indicatorId": "sl-ind-empl-fe-zs",
    "rank": 6,
    "decimal": 0
  },
  {
    "countryId": "tm",
    "date": 2023,
    "value": 26.9273914218088,
    "indicatorId": "sl-ind-empl-fe-zs",
    "rank": 7,
    "decimal": 0
  },
  {
    "countryId": "ir",
    "date": 2023,
    "value": 26.7772591687196,
    "indicatorId": "sl-ind-empl-fe-zs",
    "rank": 8,
    "decimal": 0
  },
  {
    "countryId": "mk",
    "date": 2023,
    "value": 25.1764102564103,
    "indicatorId": "sl-ind-empl-fe-zs",
    "rank": 9,
    "decimal": 0
  },
  {
    "countryId": "bj",
    "date": 2023,
    "value": 24.7036509093611,
    "indicatorId": "sl-ind-empl-fe-zs",
    "rank": 10,
    "decimal": 0
  },
  {
    "countryId": "lk",
    "date": 2023,
    "value": 24.5204873988419,
    "indicatorId": "sl-ind-empl-fe-zs",
    "rank": 11,
    "decimal": 0
  },
  {
    "countryId": "kh",
    "date": 2023,
    "value": 23.9379034539516,
    "indicatorId": "sl-ind-empl-fe-zs",
    "rank": 12,
    "decimal": 0
  },
  {
    "countryId": "st",
    "date": 2023,
    "value": 23.4046769718589,
    "indicatorId": "sl-ind-empl-fe-zs",
    "rank": 13,
    "decimal": 0
  },
  {
    "countryId": "cg",
    "date": 2023,
    "value": 23.1394416009673,
    "indicatorId": "sl-ind-empl-fe-zs",
    "rank": 14,
    "decimal": 0
  },
  {
    "countryId": "dz",
    "date": 2023,
    "value": 22.8854366910758,
    "indicatorId": "sl-ind-empl-fe-zs",
    "rank": 15,
    "decimal": 0
  },
  {
    "countryId": "bf",
    "date": 2023,
    "value": 22.8713692946058,
    "indicatorId": "sl-ind-empl-fe-zs",
    "rank": 16,
    "decimal": 0
  },
  {
    "countryId": "ro",
    "date": 2023,
    "value": 22.6120051284509,
    "indicatorId": "sl-ind-empl-fe-zs",
    "rank": 17,
    "decimal": 0
  },
  {
    "countryId": "mv",
    "date": 2023,
    "value": 22.4029274242732,
    "indicatorId": "sl-ind-empl-fe-zs",
    "rank": 18,
    "decimal": 0
  },
  {
    "countryId": "cz",
    "date": 2023,
    "value": 21.5418800486049,
    "indicatorId": "sl-ind-empl-fe-zs",
    "rank": 19,
    "decimal": 0
  },
  {
    "countryId": "bg",
    "date": 2023,
    "value": 21.248978593206,
    "indicatorId": "sl-ind-empl-fe-zs",
    "rank": 20,
    "decimal": 0
  },
  {
    "countryId": "rs",
    "date": 2023,
    "value": 19.7967618181378,
    "indicatorId": "sl-ind-empl-fe-zs",
    "rank": 21,
    "decimal": 0
  },
  {
    "countryId": "by",
    "date": 2023,
    "value": 19.693823122591,
    "indicatorId": "sl-ind-empl-fe-zs",
    "rank": 22,
    "decimal": 0
  },
  {
    "countryId": "hu",
    "date": 2023,
    "value": 19.4045180008685,
    "indicatorId": "sl-ind-empl-fe-zs",
    "rank": 23,
    "decimal": 0
  },
  {
    "countryId": "my",
    "date": 2023,
    "value": 19.0029787952289,
    "indicatorId": "sl-ind-empl-fe-zs",
    "rank": 24,
    "decimal": 0
  },
  {
    "countryId": "sk",
    "date": 2023,
    "value": 18.9840447260482,
    "indicatorId": "sl-ind-empl-fe-zs",
    "rank": 25,
    "decimal": 0
  },
  {
    "countryId": "th",
    "date": 2023,
    "value": 18.9795976754003,
    "indicatorId": "sl-ind-empl-fe-zs",
    "rank": 26,
    "decimal": 0
  },
  {
    "countryId": "mm",
    "date": 2023,
    "value": 18.3725731111479,
    "indicatorId": "sl-ind-empl-fe-zs",
    "rank": 27,
    "decimal": 0
  },
  {
    "countryId": "si",
    "date": 2023,
    "value": 18.3543690261541,
    "indicatorId": "sl-ind-empl-fe-zs",
    "rank": 28,
    "decimal": 0
  },
  {
    "countryId": "gt",
    "date": 2023,
    "value": 18.1057982054948,
    "indicatorId": "sl-ind-empl-fe-zs",
    "rank": 29,
    "decimal": 0
  },
  {
    "countryId": "tr",
    "date": 2023,
    "value": 18.0788674146922,
    "indicatorId": "sl-ind-empl-fe-zs",
    "rank": 30,
    "decimal": 0
  },
  {
    "countryId": "ng",
    "date": 2023,
    "value": 17.724505192657,
    "indicatorId": "sl-ind-empl-fe-zs",
    "rank": 31,
    "decimal": 0
  },
  {
    "countryId": "mx",
    "date": 2023,
    "value": 17.6402688369627,
    "indicatorId": "sl-ind-empl-fe-zs",
    "rank": 32,
    "decimal": 0
  },
  {
    "countryId": "bd",
    "date": 2023,
    "value": 17.5671474032078,
    "indicatorId": "sl-ind-empl-fe-zs",
    "rank": 33,
    "decimal": 0
  },
  {
    "countryId": "sv",
    "date": 2023,
    "value": 17.2725921781849,
    "indicatorId": "sl-ind-empl-fe-zs",
    "rank": 34,
    "decimal": 0
  },
  {
    "countryId": "tg",
    "date": 2023,
    "value": 17.1767821580601,
    "indicatorId": "sl-ind-empl-fe-zs",
    "rank": 35,
    "decimal": 0
  },
  {
    "countryId": "al",
    "date": 2023,
    "value": 16.7055458211066,
    "indicatorId": "sl-ind-empl-fe-zs",
    "rank": 36,
    "decimal": 0
  },
  {
    "countryId": "hn",
    "date": 2023,
    "value": 16.6769121031837,
    "indicatorId": "sl-ind-empl-fe-zs",
    "rank": 37,
    "decimal": 0
  },
  {
    "countryId": "pl",
    "date": 2023,
    "value": 16.58976496955,
    "indicatorId": "sl-ind-empl-fe-zs",
    "rank": 38,
    "decimal": 0
  },
  {
    "countryId": "lt",
    "date": 2023,
    "value": 16.4707399581362,
    "indicatorId": "sl-ind-empl-fe-zs",
    "rank": 39,
    "decimal": 0
  },
  {
    "countryId": "id",
    "date": 2023,
    "value": 16.4619167081686,
    "indicatorId": "sl-ind-empl-fe-zs",
    "rank": 40,
    "decimal": 0
  },
  {
    "countryId": "om",
    "date": 2023,
    "value": 16.1837284559568,
    "indicatorId": "sl-ind-empl-fe-zs",
    "rank": 41,
    "decimal": 0
  },
  {
    "countryId": "ga",
    "date": 2023,
    "value": 16.0530898520869,
    "indicatorId": "sl-ind-empl-fe-zs",
    "rank": 42,
    "decimal": 0
  },
  {
    "countryId": "in",
    "date": 2023,
    "value": 16.0081312172363,
    "indicatorId": "sl-ind-empl-fe-zs",
    "rank": 43,
    "decimal": 0
  },
  {
    "countryId": "ba",
    "date": 2023,
    "value": 15.852884723724,
    "indicatorId": "sl-ind-empl-fe-zs",
    "rank": 44,
    "decimal": 0
  },
  {
    "countryId": "pt",
    "date": 2023,
    "value": 15.7494164507748,
    "indicatorId": "sl-ind-empl-fe-zs",
    "rank": 45,
    "decimal": 0
  },
  {
    "countryId": "np",
    "date": 2023,
    "value": 15.5922365650462,
    "indicatorId": "sl-ind-empl-fe-zs",
    "rank": 46,
    "decimal": 0
  },
  {
    "countryId": "hr",
    "date": 2023,
    "value": 15.2730685553173,
    "indicatorId": "sl-ind-empl-fe-zs",
    "rank": 47,
    "decimal": 0
  },
  {
    "countryId": "mn",
    "date": 2023,
    "value": 15.0978679510535,
    "indicatorId": "sl-ind-empl-fe-zs",
    "rank": 48,
    "decimal": 0
  },
  {
    "countryId": "ru",
    "date": 2023,
    "value": 14.8040620945632,
    "indicatorId": "sl-ind-empl-fe-zs",
    "rank": 49,
    "decimal": 0
  },
  {
    "countryId": "gh",
    "date": 2023,
    "value": 14.7701260780274,
    "indicatorId": "sl-ind-empl-fe-zs",
    "rank": 50,
    "decimal": 0
  },
  {
    "countryId": "pk",
    "date": 2023,
    "value": 14.6684965603814,
    "indicatorId": "sl-ind-empl-fe-zs",
    "rank": 51,
    "decimal": 0
  },
  {
    "countryId": "ee",
    "date": 2023,
    "value": 14.4996758406628,
    "indicatorId": "sl-ind-empl-fe-zs",
    "rank": 52,
    "decimal": 0
  },
  {
    "countryId": "ua",
    "date": 2021,
    "value": 14.2429398220887,
    "indicatorId": "sl-ind-empl-fe-zs",
    "rank": 53,
    "decimal": 0
  },
  {
    "countryId": "sz",
    "date": 2023,
    "value": 14.2178944019291,
    "indicatorId": "sl-ind-empl-fe-zs",
    "rank": 54,
    "decimal": 0
  },
  {
    "countryId": "uz",
    "date": 2023,
    "value": 14.1121641330413,
    "indicatorId": "sl-ind-empl-fe-zs",
    "rank": 55,
    "decimal": 0
  },
  {
    "countryId": "ma",
    "date": 2023,
    "value": 13.8286425143536,
    "indicatorId": "sl-ind-empl-fe-zs",
    "rank": 56,
    "decimal": 0
  },
  {
    "countryId": "it",
    "date": 2023,
    "value": 13.7589931867715,
    "indicatorId": "sl-ind-empl-fe-zs",
    "rank": 57,
    "decimal": 0
  },
  {
    "countryId": "td",
    "date": 2023,
    "value": 13.7380081882433,
    "indicatorId": "sl-ind-empl-fe-zs",
    "rank": 58,
    "decimal": 0
  },
  {
    "countryId": "jp",
    "date": 2023,
    "value": 13.6967940881855,
    "indicatorId": "sl-ind-empl-fe-zs",
    "rank": 59,
    "decimal": 0
  },
  {
    "countryId": "so",
    "date": 2023,
    "value": 13.5891980569832,
    "indicatorId": "sl-ind-empl-fe-zs",
    "rank": 60,
    "decimal": 0
  },
  {
    "countryId": "ni",
    "date": 2023,
    "value": 13.3062139247732,
    "indicatorId": "sl-ind-empl-fe-zs",
    "rank": 61,
    "decimal": 0
  },
  {
    "countryId": "de",
    "date": 2023,
    "value": 13.1641660857864,
    "indicatorId": "sl-ind-empl-fe-zs",
    "rank": 62,
    "decimal": 0
  },
  {
    "countryId": "co",
    "date": 2023,
    "value": 13.1404584122279,
    "indicatorId": "sl-ind-empl-fe-zs",
    "rank": 63,
    "decimal": 0
  },
  {
    "countryId": "tt",
    "date": 2023,
    "value": 13.1231624857105,
    "indicatorId": "sl-ind-empl-fe-zs",
    "rank": 64,
    "decimal": 0
  },
  {
    "countryId": "gw",
    "date": 2023,
    "value": 12.8550431550094,
    "indicatorId": "sl-ind-empl-fe-zs",
    "rank": 65,
    "decimal": 0
  },
  {
    "countryId": "ye",
    "date": 2023,
    "value": 12.8414306573708,
    "indicatorId": "sl-ind-empl-fe-zs",
    "rank": 66,
    "decimal": 0
  },
  {
    "countryId": "at",
    "date": 2023,
    "value": 12.8055322478764,
    "indicatorId": "sl-ind-empl-fe-zs",
    "rank": 67,
    "decimal": 0
  },
  {
    "countryId": "kr",
    "date": 2023,
    "value": 12.7540880117472,
    "indicatorId": "sl-ind-empl-fe-zs",
    "rank": 68,
    "decimal": 0
  },
  {
    "countryId": "bo",
    "date": 2023,
    "value": 12.6456286183978,
    "indicatorId": "sl-ind-empl-fe-zs",
    "rank": 69,
    "decimal": 0
  },
  {
    "countryId": "lv",
    "date": 2023,
    "value": 12.4733168452872,
    "indicatorId": "sl-ind-empl-fe-zs",
    "rank": 70,
    "decimal": 0
  },
  {
    "countryId": "cr",
    "date": 2023,
    "value": 12.297124458407,
    "indicatorId": "sl-ind-empl-fe-zs",
    "rank": 71,
    "decimal": 0
  },
  {
    "countryId": "cm",
    "date": 2023,
    "value": 12.1900635348298,
    "indicatorId": "sl-ind-empl-fe-zs",
    "rank": 72,
    "decimal": 0
  },
  {
    "countryId": "kg",
    "date": 2023,
    "value": 12.1514967618057,
    "indicatorId": "sl-ind-empl-fe-zs",
    "rank": 73,
    "decimal": 0
  },
  {
    "countryId": "kz",
    "date": 2023,
    "value": 11.8180490781086,
    "indicatorId": "sl-ind-empl-fe-zs",
    "rank": 74,
    "decimal": 0
  },
  {
    "countryId": "sr",
    "date": 2023,
    "value": 11.509444058002,
    "indicatorId": "sl-ind-empl-fe-zs",
    "rank": 75,
    "decimal": 0
  },
  {
    "countryId": "cv",
    "date": 2023,
    "value": 11.3251619144242,
    "indicatorId": "sl-ind-empl-fe-zs",
    "rank": 76,
    "decimal": 0
  },
  {
    "countryId": "iq",
    "date": 2023,
    "value": 11.2704125670492,
    "indicatorId": "sl-ind-empl-fe-zs",
    "rank": 77,
    "decimal": 0
  },
  {
    "countryId": "ml",
    "date": 2023,
    "value": 11.2147666918774,
    "indicatorId": "sl-ind-empl-fe-zs",
    "rank": 78,
    "decimal": 0
  },
  {
    "countryId": "sn",
    "date": 2023,
    "value": 11.0807794972421,
    "indicatorId": "sl-ind-empl-fe-zs",
    "rank": 79,
    "decimal": 0
  },
  {
    "countryId": "ve",
    "date": 2023,
    "value": 10.9696161895089,
    "indicatorId": "sl-ind-empl-fe-zs",
    "rank": 80,
    "decimal": 0
  },
  {
    "countryId": "gy",
    "date": 2023,
    "value": 10.8867477135007,
    "indicatorId": "sl-ind-empl-fe-zs",
    "rank": 81,
    "decimal": 0
  },
  {
    "countryId": "cl",
    "date": 2023,
    "value": 10.7143540424925,
    "indicatorId": "sl-ind-empl-fe-zs",
    "rank": 82,
    "decimal": 0
  },
  {
    "countryId": "bt",
    "date": 2023,
    "value": 10.6615502288137,
    "indicatorId": "sl-ind-empl-fe-zs",
    "rank": 83,
    "decimal": 0
  },
  {
    "countryId": "ht",
    "date": 2023,
    "value": 10.6401152875707,
    "indicatorId": "sl-ind-empl-fe-zs",
    "rank": 84,
    "decimal": 0
  },
  {
    "countryId": "br",
    "date": 2023,
    "value": 10.5907273741684,
    "indicatorId": "sl-ind-empl-fe-zs",
    "rank": 85,
    "decimal": 0
  },
  {
    "countryId": "km",
    "date": 2023,
    "value": 10.5322037787807,
    "indicatorId": "sl-ind-empl-fe-zs",
    "rank": 86,
    "decimal": 0
  },
  {
    "countryId": "sg",
    "date": 2023,
    "value": 10.5100553021215,
    "indicatorId": "sl-ind-empl-fe-zs",
    "rank": 87,
    "decimal": 0
  },
  {
    "countryId": "mu",
    "date": 2023,
    "value": 10.4934184265273,
    "indicatorId": "sl-ind-empl-fe-zs",
    "rank": 88,
    "decimal": 0
  },
  {
    "countryId": "mr",
    "date": 2023,
    "value": 10.2442478942848,
    "indicatorId": "sl-ind-empl-fe-zs",
    "rank": 89,
    "decimal": 0
  },
  {
    "countryId": "ar",
    "date": 2023,
    "value": 10.2305445864573,
    "indicatorId": "sl-ind-empl-fe-zs",
    "rank": 90,
    "decimal": 0
  },
  {
    "countryId": "bh",
    "date": 2023,
    "value": 10.2183546853598,
    "indicatorId": "sl-ind-empl-fe-zs",
    "rank": 91,
    "decimal": 0
  },
  {
    "countryId": "ke",
    "date": 2023,
    "value": 10.1746063512535,
    "indicatorId": "sl-ind-empl-fe-zs",
    "rank": 92,
    "decimal": 0
  },
  {
    "countryId": "bz",
    "date": 2023,
    "value": 10.0307030531615,
    "indicatorId": "sl-ind-empl-fe-zs",
    "rank": 93,
    "decimal": 0
  },
  {
    "countryId": "nz",
    "date": 2023,
    "value": 10.0116859445993,
    "indicatorId": "sl-ind-empl-fe-zs",
    "rank": 94,
    "decimal": 0
  },
  {
    "countryId": "pa",
    "date": 2023,
    "value": 9.88856631045772,
    "indicatorId": "sl-ind-empl-fe-zs",
    "rank": 95,
    "decimal": 0
  },
  {
    "countryId": "fr",
    "date": 2023,
    "value": 9.78480616444354,
    "indicatorId": "sl-ind-empl-fe-zs",
    "rank": 96,
    "decimal": 0
  },
  {
    "countryId": "ch",
    "date": 2023,
    "value": 9.77717775476681,
    "indicatorId": "sl-ind-empl-fe-zs",
    "rank": 97,
    "decimal": 0
  },
  {
    "countryId": "cu",
    "date": 2023,
    "value": 9.75033644053427,
    "indicatorId": "sl-ind-empl-fe-zs",
    "rank": 98,
    "decimal": 0
  },
  {
    "countryId": "dk",
    "date": 2023,
    "value": 9.60752744380554,
    "indicatorId": "sl-ind-empl-fe-zs",
    "rank": 99,
    "decimal": 0
  },
  {
    "countryId": "ne",
    "date": 2023,
    "value": 9.59793724791838,
    "indicatorId": "sl-ind-empl-fe-zs",
    "rank": 100,
    "decimal": 0
  },
  {
    "countryId": "fi",
    "date": 2023,
    "value": 9.55445510395128,
    "indicatorId": "sl-ind-empl-fe-zs",
    "rank": 101,
    "decimal": 0
  },
  {
    "countryId": "ie",
    "date": 2023,
    "value": 9.53431219122767,
    "indicatorId": "sl-ind-empl-fe-zs",
    "rank": 102,
    "decimal": 0
  },
  {
    "countryId": "ec",
    "date": 2023,
    "value": 9.5324157637661,
    "indicatorId": "sl-ind-empl-fe-zs",
    "rank": 103,
    "decimal": 0
  },
  {
    "countryId": "mg",
    "date": 2023,
    "value": 9.39037217209003,
    "indicatorId": "sl-ind-empl-fe-zs",
    "rank": 104,
    "decimal": 0
  },
  {
    "countryId": "bn",
    "date": 2023,
    "value": 9.38022464501848,
    "indicatorId": "sl-ind-empl-fe-zs",
    "rank": 105,
    "decimal": 0
  },
  {
    "countryId": "kp",
    "date": 2023,
    "value": 9.30976101328114,
    "indicatorId": "sl-ind-empl-fe-zs",
    "rank": 106,
    "decimal": 0
  },
  {
    "countryId": "ly",
    "date": 2023,
    "value": 9.23624546343095,
    "indicatorId": "sl-ind-empl-fe-zs",
    "rank": 107,
    "decimal": 0
  },
  {
    "countryId": "es",
    "date": 2023,
    "value": 9.14434408845263,
    "indicatorId": "sl-ind-empl-fe-zs",
    "rank": 108,
    "decimal": 0
  },
  {
    "countryId": "za",
    "date": 2023,
    "value": 8.91590242379269,
    "indicatorId": "sl-ind-empl-fe-zs",
    "rank": 109,
    "decimal": 0
  },
  {
    "countryId": "pe",
    "date": 2023,
    "value": 8.85443282882463,
    "indicatorId": "sl-ind-empl-fe-zs",
    "rank": 110,
    "decimal": 0
  },
  {
    "countryId": "uy",
    "date": 2023,
    "value": 8.83224070482926,
    "indicatorId": "sl-ind-empl-fe-zs",
    "rank": 111,
    "decimal": 0
  },
  {
    "countryId": "ph",
    "date": 2023,
    "value": 8.79288277611528,
    "indicatorId": "sl-ind-empl-fe-zs",
    "rank": 112,
    "decimal": 0
  },
  {
    "countryId": "bw",
    "date": 2023,
    "value": 8.74489725493404,
    "indicatorId": "sl-ind-empl-fe-zs",
    "rank": 113,
    "decimal": 0
  },
  {
    "countryId": "bb",
    "date": 2023,
    "value": 8.67388520200256,
    "indicatorId": "sl-ind-empl-fe-zs",
    "rank": 114,
    "decimal": 0
  },
  {
    "countryId": "ca",
    "date": 2023,
    "value": 8.64591426688283,
    "indicatorId": "sl-ind-empl-fe-zs",
    "rank": 115,
    "decimal": 0
  },
  {
    "countryId": "us",
    "date": 2023,
    "value": 8.64061996381687,
    "indicatorId": "sl-ind-empl-fe-zs",
    "rank": 116,
    "decimal": 0
  },
  {
    "countryId": "mt",
    "date": 2023,
    "value": 8.58582883875908,
    "indicatorId": "sl-ind-empl-fe-zs",
    "rank": 117,
    "decimal": 0
  },
  {
    "countryId": "eg",
    "date": 2023,
    "value": 8.46116450735489,
    "indicatorId": "sl-ind-empl-fe-zs",
    "rank": 118,
    "decimal": 0
  },
  {
    "countryId": "md",
    "date": 2023,
    "value": 8.4171125278997,
    "indicatorId": "sl-ind-empl-fe-zs",
    "rank": 119,
    "decimal": 0
  },
  {
    "countryId": "py",
    "date": 2023,
    "value": 8.25904495548673,
    "indicatorId": "sl-ind-empl-fe-zs",
    "rank": 120,
    "decimal": 0
  },
  {
    "countryId": "do",
    "date": 2023,
    "value": 8.17393923153014,
    "indicatorId": "sl-ind-empl-fe-zs",
    "rank": 121,
    "decimal": 0
  },
  {
    "countryId": "gr",
    "date": 2023,
    "value": 8.0921046288803,
    "indicatorId": "sl-ind-empl-fe-zs",
    "rank": 122,
    "decimal": 0
  },
  {
    "countryId": "au",
    "date": 2023,
    "value": 7.978684444329,
    "indicatorId": "sl-ind-empl-fe-zs",
    "rank": 123,
    "decimal": 0
  },
  {
    "countryId": "be",
    "date": 2023,
    "value": 7.88552797427436,
    "indicatorId": "sl-ind-empl-fe-zs",
    "rank": 124,
    "decimal": 0
  },
  {
    "countryId": "na",
    "date": 2023,
    "value": 7.78437894253928,
    "indicatorId": "sl-ind-empl-fe-zs",
    "rank": 125,
    "decimal": 0
  },
  {
    "countryId": "gb",
    "date": 2023,
    "value": 7.75083222157605,
    "indicatorId": "sl-ind-empl-fe-zs",
    "rank": 126,
    "decimal": 0
  },
  {
    "countryId": "kw",
    "date": 2023,
    "value": 7.69437702326509,
    "indicatorId": "sl-ind-empl-fe-zs",
    "rank": 127,
    "decimal": 0
  },
  {
    "countryId": "ws",
    "date": 2023,
    "value": 7.57717980809345,
    "indicatorId": "sl-ind-empl-fe-zs",
    "rank": 128,
    "decimal": 0
  },
  {
    "countryId": "il",
    "date": 2023,
    "value": 7.51916673024811,
    "indicatorId": "sl-ind-empl-fe-zs",
    "rank": 129,
    "decimal": 0
  },
  {
    "countryId": "fj",
    "date": 2023,
    "value": 7.47304907481899,
    "indicatorId": "sl-ind-empl-fe-zs",
    "rank": 130,
    "decimal": 0
  },
  {
    "countryId": "lc",
    "date": 2023,
    "value": 7.43107980994187,
    "indicatorId": "sl-ind-empl-fe-zs",
    "rank": 131,
    "decimal": 0
  },
  {
    "countryId": "rw",
    "date": 2023,
    "value": 7.39641726675547,
    "indicatorId": "sl-ind-empl-fe-zs",
    "rank": 132,
    "decimal": 0
  },
  {
    "countryId": "ss",
    "date": 2023,
    "value": 7.348340099225,
    "indicatorId": "sl-ind-empl-fe-zs",
    "rank": 133,
    "decimal": 0
  },
  {
    "countryId": "se",
    "date": 2023,
    "value": 7.31893071714148,
    "indicatorId": "sl-ind-empl-fe-zs",
    "rank": 134,
    "decimal": 0
  },
  {
    "countryId": "is",
    "date": 2023,
    "value": 7.25955901819145,
    "indicatorId": "sl-ind-empl-fe-zs",
    "rank": 135,
    "decimal": 0
  },
  {
    "countryId": "tl",
    "date": 2023,
    "value": 7.0559557031138,
    "indicatorId": "sl-ind-empl-fe-zs",
    "rank": 136,
    "decimal": 0
  },
  {
    "countryId": "cy",
    "date": 2023,
    "value": 7.01190580859146,
    "indicatorId": "sl-ind-empl-fe-zs",
    "rank": 137,
    "decimal": 0
  },
  {
    "countryId": "no",
    "date": 2023,
    "value": 6.92984955758678,
    "indicatorId": "sl-ind-empl-fe-zs",
    "rank": 138,
    "decimal": 0
  },
  {
    "countryId": "jo",
    "date": 2023,
    "value": 6.92082262210797,
    "indicatorId": "sl-ind-empl-fe-zs",
    "rank": 139,
    "decimal": 0
  },
  {
    "countryId": "ae",
    "date": 2023,
    "value": 6.61855427499788,
    "indicatorId": "sl-ind-empl-fe-zs",
    "rank": 140,
    "decimal": 0
  },
  {
    "countryId": "az",
    "date": 2023,
    "value": 6.40261746245666,
    "indicatorId": "sl-ind-empl-fe-zs",
    "rank": 141,
    "decimal": 0
  },
  {
    "countryId": "lb",
    "date": 2023,
    "value": 6.26589688723808,
    "indicatorId": "sl-ind-empl-fe-zs",
    "rank": 142,
    "decimal": 0
  },
  {
    "countryId": "cd",
    "date": 2023,
    "value": 6.21385352594099,
    "indicatorId": "sl-ind-empl-fe-zs",
    "rank": 143,
    "decimal": 0
  },
  {
    "countryId": "sy",
    "date": 2023,
    "value": 6.17558920229239,
    "indicatorId": "sl-ind-empl-fe-zs",
    "rank": 144,
    "decimal": 0
  },
  {
    "countryId": "me",
    "date": 2023,
    "value": 6.08912792931233,
    "indicatorId": "sl-ind-empl-fe-zs",
    "rank": 145,
    "decimal": 0
  },
  {
    "countryId": "tj",
    "date": 2023,
    "value": 5.95468881705808,
    "indicatorId": "sl-ind-empl-fe-zs",
    "rank": 146,
    "decimal": 0
  },
  {
    "countryId": "ci",
    "date": 2023,
    "value": 5.90919217851331,
    "indicatorId": "sl-ind-empl-fe-zs",
    "rank": 147,
    "decimal": 0
  },
  {
    "countryId": "jm",
    "date": 2023,
    "value": 5.86761836218346,
    "indicatorId": "sl-ind-empl-fe-zs",
    "rank": 148,
    "decimal": 0
  },
  {
    "countryId": "ge",
    "date": 2023,
    "value": 5.86263359369814,
    "indicatorId": "sl-ind-empl-fe-zs",
    "rank": 149,
    "decimal": 0
  },
  {
    "countryId": "sl",
    "date": 2023,
    "value": 5.85947061614382,
    "indicatorId": "sl-ind-empl-fe-zs",
    "rank": 150,
    "decimal": 0
  },
  {
    "countryId": "nl",
    "date": 2023,
    "value": 5.78804430409473,
    "indicatorId": "sl-ind-empl-fe-zs",
    "rank": 151,
    "decimal": 0
  },
  {
    "countryId": "er",
    "date": 2023,
    "value": 5.70815971519883,
    "indicatorId": "sl-ind-empl-fe-zs",
    "rank": 152,
    "decimal": 0
  },
  {
    "countryId": "la",
    "date": 2023,
    "value": 5.60627455625244,
    "indicatorId": "sl-ind-empl-fe-zs",
    "rank": 153,
    "decimal": 0
  },
  {
    "countryId": "sa",
    "date": 2023,
    "value": 5.44768964690434,
    "indicatorId": "sl-ind-empl-fe-zs",
    "rank": 154,
    "decimal": 0
  },
  {
    "countryId": "vc",
    "date": 2023,
    "value": 5.43249529294495,
    "indicatorId": "sl-ind-empl-fe-zs",
    "rank": 155,
    "decimal": 0
  },
  {
    "countryId": "mw",
    "date": 2023,
    "value": 5.25754707374905,
    "indicatorId": "sl-ind-empl-fe-zs",
    "rank": 156,
    "decimal": 0
  },
  {
    "countryId": "vu",
    "date": 2023,
    "value": 5.18029762143516,
    "indicatorId": "sl-ind-empl-fe-zs",
    "rank": 157,
    "decimal": 0
  },
  {
    "countryId": "gm",
    "date": 2023,
    "value": 5.02667700569418,
    "indicatorId": "sl-ind-empl-fe-zs",
    "rank": 158,
    "decimal": 0
  },
  {
    "countryId": "et",
    "date": 2023,
    "value": 4.8573252921823,
    "indicatorId": "sl-ind-empl-fe-zs",
    "rank": 159,
    "decimal": 0
  },
  {
    "countryId": "cf",
    "date": 2023,
    "value": 4.85368715649687,
    "indicatorId": "sl-ind-empl-fe-zs",
    "rank": 160,
    "decimal": 0
  },
  {
    "countryId": "gq",
    "date": 2023,
    "value": 4.84311318824844,
    "indicatorId": "sl-ind-empl-fe-zs",
    "rank": 161,
    "decimal": 0
  },
  {
    "countryId": "tz",
    "date": 2023,
    "value": 4.68016800076664,
    "indicatorId": "sl-ind-empl-fe-zs",
    "rank": 162,
    "decimal": 0
  },
  {
    "countryId": "sb",
    "date": 2023,
    "value": 4.59724125513889,
    "indicatorId": "sl-ind-empl-fe-zs",
    "rank": 163,
    "decimal": 0
  },
  {
    "countryId": "am",
    "date": 2023,
    "value": 4.58305353291227,
    "indicatorId": "sl-ind-empl-fe-zs",
    "rank": 164,
    "decimal": 0
  },
  {
    "countryId": "lr",
    "date": 2023,
    "value": 4.15083610075604,
    "indicatorId": "sl-ind-empl-fe-zs",
    "rank": 165,
    "decimal": 0
  },
  {
    "countryId": "qa",
    "date": 2023,
    "value": 3.92401231141834,
    "indicatorId": "sl-ind-empl-fe-zs",
    "rank": 166,
    "decimal": 0
  },
  {
    "countryId": "zm",
    "date": 2023,
    "value": 3.92331828249908,
    "indicatorId": "sl-ind-empl-fe-zs",
    "rank": 167,
    "decimal": 0
  },
  {
    "countryId": "zw",
    "date": 2023,
    "value": 3.89053514011809,
    "indicatorId": "sl-ind-empl-fe-zs",
    "rank": 168,
    "decimal": 0
  },
  {
    "countryId": "lu",
    "date": 2023,
    "value": 3.81361266257213,
    "indicatorId": "sl-ind-empl-fe-zs",
    "rank": 169,
    "decimal": 0
  },
  {
    "countryId": "ug",
    "date": 2023,
    "value": 3.62214963955516,
    "indicatorId": "sl-ind-empl-fe-zs",
    "rank": 170,
    "decimal": 0
  },
  {
    "countryId": "bs",
    "date": 2023,
    "value": 3.46852563981132,
    "indicatorId": "sl-ind-empl-fe-zs",
    "rank": 171,
    "decimal": 0
  },
  {
    "countryId": "mz",
    "date": 2023,
    "value": 3.38705252588319,
    "indicatorId": "sl-ind-empl-fe-zs",
    "rank": 172,
    "decimal": 0
  },
  {
    "countryId": "sd",
    "date": 2022,
    "value": 2.72378600103694,
    "indicatorId": "sl-ind-empl-fe-zs",
    "rank": 173,
    "decimal": 0
  },
  {
    "countryId": "gn",
    "date": 2023,
    "value": 2.42272390842931,
    "indicatorId": "sl-ind-empl-fe-zs",
    "rank": 174,
    "decimal": 0
  },
  {
    "countryId": "pg",
    "date": 2023,
    "value": 2.07602647173008,
    "indicatorId": "sl-ind-empl-fe-zs",
    "rank": 175,
    "decimal": 0
  },
  {
    "countryId": "ao",
    "date": 2023,
    "value": 1.06907083836472,
    "indicatorId": "sl-ind-empl-fe-zs",
    "rank": 176,
    "decimal": 0
  },
  {
    "countryId": "dj",
    "date": 2023,
    "value": 0.734966592427617,
    "indicatorId": "sl-ind-empl-fe-zs",
    "rank": 177,
    "decimal": 0
  },
  {
    "countryId": "bi",
    "date": 2023,
    "value": 0.546957499271131,
    "indicatorId": "sl-ind-empl-fe-zs",
    "rank": 178,
    "decimal": 0
  }
]