[
  {
    "indicatorId": "dc-dac-czel-cd",
    "value": 1499.000005,
    "date": 2022,
    "type": "min"
  },
  {
    "indicatorId": "ic-bre-mc-os",
    "value": 68.551057,
    "date": 2024,
    "type": "max"
  },
  {
    "indicatorId": "ic-bre-mc-p3",
    "value": 69.805551,
    "date": 2024,
    "type": "max"
  },
  {
    "indicatorId": "per_lm_alllm-cov_pop_tot",
    "value": 19.024478,
    "date": 2022,
    "type": "max"
  },
  {
    "indicatorId": "per_lm_alllm-cov_q1_tot",
    "value": 16.481933,
    "date": 2022,
    "type": "max"
  },
  {
    "indicatorId": "per_lm_alllm-cov_q2_tot",
    "value": 20.850444,
    "date": 2022,
    "type": "max"
  },
  {
    "indicatorId": "per_lm_alllm-cov_q3_tot",
    "value": 20.320513,
    "date": 2022,
    "type": "max"
  },
  {
    "indicatorId": "per_lm_alllm-cov_q4_tot",
    "value": 21.341611,
    "date": 2022,
    "type": "max"
  },
  {
    "indicatorId": "per_lm_alllm-cov_q5_tot",
    "value": 16.127727,
    "date": 2022,
    "type": "max"
  },
  {
    "indicatorId": "sl-agr-0714-fe-zs",
    "value": 20.16,
    "date": 2016,
    "type": "min"
  },
  {
    "indicatorId": "sl-agr-0714-zs",
    "value": 36.6,
    "date": 2016,
    "type": "min"
  },
  {
    "indicatorId": "sl-fam-0714-fe-zs",
    "value": 54.59,
    "date": 2016,
    "type": "min"
  },
  {
    "indicatorId": "sl-srv-0714-fe-zs",
    "value": 79.84,
    "date": 2016,
    "type": "max"
  },
  {
    "indicatorId": "sl-srv-0714-ma-zs",
    "value": 45.5,
    "date": 2016,
    "type": "max"
  },
  {
    "indicatorId": "sl-srv-0714-zs",
    "value": 53.5,
    "date": 2016,
    "type": "max"
  },
  {
    "indicatorId": "sl-tlf-0714-ma-zs",
    "value": 1.94,
    "date": 2016,
    "type": "min"
  },
  {
    "indicatorId": "sl-tlf-0714-wk-fe-tm",
    "value": 44.16,
    "date": 2016,
    "type": "max"
  },
  {
    "indicatorId": "sl-wag-0714-fe-zs",
    "value": 45.4,
    "date": 2016,
    "type": "max"
  },
  {
    "indicatorId": "sl-wag-0714-zs",
    "value": 27.88,
    "date": 2016,
    "type": "max"
  }
]