[
  {
    "countryId": "br",
    "date": 2023,
    "value": 1106842805.38,
    "indicatorId": "dt-nfl-nifc-cd",
    "rank": 1,
    "decimal": 0
  },
  {
    "countryId": "tr",
    "date": 2023,
    "value": 790753240.74,
    "indicatorId": "dt-nfl-nifc-cd",
    "rank": 2,
    "decimal": 0
  },
  {
    "countryId": "za",
    "date": 2023,
    "value": 538883425.62,
    "indicatorId": "dt-nfl-nifc-cd",
    "rank": 3,
    "decimal": 0
  },
  {
    "countryId": "th",
    "date": 2023,
    "value": 445281744.27,
    "indicatorId": "dt-nfl-nifc-cd",
    "rank": 4,
    "decimal": 0
  },
  {
    "countryId": "vn",
    "date": 2023,
    "value": 379518426.57,
    "indicatorId": "dt-nfl-nifc-cd",
    "rank": 5,
    "decimal": 0
  },
  {
    "countryId": "co",
    "date": 2023,
    "value": 273707597.04,
    "indicatorId": "dt-nfl-nifc-cd",
    "rank": 6,
    "decimal": 0
  },
  {
    "countryId": "eg",
    "date": 2023,
    "value": 178354698.08,
    "indicatorId": "dt-nfl-nifc-cd",
    "rank": 7,
    "decimal": 0
  },
  {
    "countryId": "gt",
    "date": 2023,
    "value": 159500362.29,
    "indicatorId": "dt-nfl-nifc-cd",
    "rank": 8,
    "decimal": 0
  },
  {
    "countryId": "in",
    "date": 2023,
    "value": 151753805.03,
    "indicatorId": "dt-nfl-nifc-cd",
    "rank": 9,
    "decimal": 0
  },
  {
    "countryId": "id",
    "date": 2023,
    "value": 133866800.43,
    "indicatorId": "dt-nfl-nifc-cd",
    "rank": 10,
    "decimal": 0
  },
  {
    "countryId": "ma",
    "date": 2023,
    "value": 123610259.3,
    "indicatorId": "dt-nfl-nifc-cd",
    "rank": 11,
    "decimal": 0
  },
  {
    "countryId": "ph",
    "date": 2023,
    "value": 99381916.98,
    "indicatorId": "dt-nfl-nifc-cd",
    "rank": 12,
    "decimal": 0
  },
  {
    "countryId": "kz",
    "date": 2023,
    "value": 91562078.52,
    "indicatorId": "dt-nfl-nifc-cd",
    "rank": 13,
    "decimal": 0
  },
  {
    "countryId": "mn",
    "date": 2023,
    "value": 79331733.65,
    "indicatorId": "dt-nfl-nifc-cd",
    "rank": 14,
    "decimal": 0
  },
  {
    "countryId": "ci",
    "date": 2023,
    "value": 75264544.19,
    "indicatorId": "dt-nfl-nifc-cd",
    "rank": 15,
    "decimal": 0
  },
  {
    "countryId": "et",
    "date": 2023,
    "value": 75000000,
    "indicatorId": "dt-nfl-nifc-cd",
    "rank": 16,
    "decimal": 0
  },
  {
    "countryId": "cd",
    "date": 2023,
    "value": 73000000,
    "indicatorId": "dt-nfl-nifc-cd",
    "rank": 17,
    "decimal": 0
  },
  {
    "countryId": "pe",
    "date": 2023,
    "value": 68350419.05,
    "indicatorId": "dt-nfl-nifc-cd",
    "rank": 18,
    "decimal": 0
  },
  {
    "countryId": "rs",
    "date": 2023,
    "value": 62404018.07,
    "indicatorId": "dt-nfl-nifc-cd",
    "rank": 19,
    "decimal": 0
  },
  {
    "countryId": "uz",
    "date": 2023,
    "value": 58697003.29,
    "indicatorId": "dt-nfl-nifc-cd",
    "rank": 20,
    "decimal": 0
  },
  {
    "countryId": "do",
    "date": 2023,
    "value": 51641448.49,
    "indicatorId": "dt-nfl-nifc-cd",
    "rank": 21,
    "decimal": 0
  },
  {
    "countryId": "ng",
    "date": 2023,
    "value": 51303773.23,
    "indicatorId": "dt-nfl-nifc-cd",
    "rank": 22,
    "decimal": 0
  },
  {
    "countryId": "bd",
    "date": 2023,
    "value": 42541191.39,
    "indicatorId": "dt-nfl-nifc-cd",
    "rank": 23,
    "decimal": 0
  },
  {
    "countryId": "sn",
    "date": 2023,
    "value": 41664335.57,
    "indicatorId": "dt-nfl-nifc-cd",
    "rank": 24,
    "decimal": 0
  },
  {
    "countryId": "al",
    "date": 2023,
    "value": 31783087.82,
    "indicatorId": "dt-nfl-nifc-cd",
    "rank": 25,
    "decimal": 0
  },
  {
    "countryId": "cm",
    "date": 2023,
    "value": 31174265.58,
    "indicatorId": "dt-nfl-nifc-cd",
    "rank": 26,
    "decimal": 0
  },
  {
    "countryId": "tz",
    "date": 2023,
    "value": 30468881.31,
    "indicatorId": "dt-nfl-nifc-cd",
    "rank": 27,
    "decimal": 0
  },
  {
    "countryId": "mz",
    "date": 2023,
    "value": 26254988.65,
    "indicatorId": "dt-nfl-nifc-cd",
    "rank": 28,
    "decimal": 0
  },
  {
    "countryId": "mg",
    "date": 2023,
    "value": 25558385.29,
    "indicatorId": "dt-nfl-nifc-cd",
    "rank": 29,
    "decimal": 0
  },
  {
    "countryId": "ne",
    "date": 2023,
    "value": 24925803.48,
    "indicatorId": "dt-nfl-nifc-cd",
    "rank": 30,
    "decimal": 0
  },
  {
    "countryId": "cv",
    "date": 2023,
    "value": 24916474.67,
    "indicatorId": "dt-nfl-nifc-cd",
    "rank": 31,
    "decimal": 0
  },
  {
    "countryId": "bw",
    "date": 2022,
    "value": 24838083,
    "indicatorId": "dt-nfl-nifc-cd",
    "rank": 32,
    "decimal": 0
  },
  {
    "countryId": "mx",
    "date": 2023,
    "value": 23724076.61,
    "indicatorId": "dt-nfl-nifc-cd",
    "rank": 33,
    "decimal": 0
  },
  {
    "countryId": "ga",
    "date": 2023,
    "value": 21515859.61,
    "indicatorId": "dt-nfl-nifc-cd",
    "rank": 34,
    "decimal": 0
  },
  {
    "countryId": "az",
    "date": 2023,
    "value": 20000000,
    "indicatorId": "dt-nfl-nifc-cd",
    "rank": 35,
    "decimal": 0
  },
  {
    "countryId": "ec",
    "date": 2023,
    "value": 19179372.46,
    "indicatorId": "dt-nfl-nifc-cd",
    "rank": 36,
    "decimal": 0
  },
  {
    "countryId": "kg",
    "date": 2023,
    "value": 17496788.39,
    "indicatorId": "dt-nfl-nifc-cd",
    "rank": 37,
    "decimal": 0
  },
  {
    "countryId": "py",
    "date": 2023,
    "value": 16666666.6,
    "indicatorId": "dt-nfl-nifc-cd",
    "rank": 38,
    "decimal": 0
  },
  {
    "countryId": "ke",
    "date": 2023,
    "value": 13481912.13,
    "indicatorId": "dt-nfl-nifc-cd",
    "rank": 39,
    "decimal": 0
  },
  {
    "countryId": "la",
    "date": 2023,
    "value": 12457934.58,
    "indicatorId": "dt-nfl-nifc-cd",
    "rank": 40,
    "decimal": 0
  },
  {
    "countryId": "bf",
    "date": 2023,
    "value": 11463745.76,
    "indicatorId": "dt-nfl-nifc-cd",
    "rank": 41,
    "decimal": 0
  },
  {
    "countryId": "np",
    "date": 2023,
    "value": 11000000,
    "indicatorId": "dt-nfl-nifc-cd",
    "rank": 42,
    "decimal": 0
  },
  {
    "countryId": "md",
    "date": 2023,
    "value": 10489394.21,
    "indicatorId": "dt-nfl-nifc-cd",
    "rank": 43,
    "decimal": 0
  },
  {
    "countryId": "cg",
    "date": 2023,
    "value": 9852116.83,
    "indicatorId": "dt-nfl-nifc-cd",
    "rank": 44,
    "decimal": 0
  },
  {
    "countryId": "cn",
    "date": 2023,
    "value": 5840006.89,
    "indicatorId": "dt-nfl-nifc-cd",
    "rank": 45,
    "decimal": 0
  },
  {
    "countryId": "lr",
    "date": 2022,
    "value": 5400000,
    "indicatorId": "dt-nfl-nifc-cd",
    "rank": 46,
    "decimal": 0
  },
  {
    "countryId": "zm",
    "date": 2023,
    "value": 3828100.92,
    "indicatorId": "dt-nfl-nifc-cd",
    "rank": 47,
    "decimal": 0
  },
  {
    "countryId": "sl",
    "date": 2022,
    "value": 1250000,
    "indicatorId": "dt-nfl-nifc-cd",
    "rank": 48,
    "decimal": 0
  },
  {
    "countryId": "ml",
    "date": 2023,
    "value": 769344.54,
    "indicatorId": "dt-nfl-nifc-cd",
    "rank": 49,
    "decimal": 0
  },
  {
    "countryId": "tn",
    "date": 2023,
    "value": 429284.09,
    "indicatorId": "dt-nfl-nifc-cd",
    "rank": 50,
    "decimal": 0
  },
  {
    "countryId": "ba",
    "date": 2023,
    "value": -249587.91,
    "indicatorId": "dt-nfl-nifc-cd",
    "rank": 51,
    "decimal": 0
  },
  {
    "countryId": "gm",
    "date": 2023,
    "value": -306507.21,
    "indicatorId": "dt-nfl-nifc-cd",
    "rank": 52,
    "decimal": 0
  },
  {
    "countryId": "tl",
    "date": 2023,
    "value": -437500,
    "indicatorId": "dt-nfl-nifc-cd",
    "rank": 53,
    "decimal": 0
  },
  {
    "countryId": "bo",
    "date": 2022,
    "value": -566107,
    "indicatorId": "dt-nfl-nifc-cd",
    "rank": 54,
    "decimal": 0
  },
  {
    "countryId": "mw",
    "date": 2023,
    "value": -600000,
    "indicatorId": "dt-nfl-nifc-cd",
    "rank": 55,
    "decimal": 0
  },
  {
    "countryId": "gd",
    "date": 2018,
    "value": -878626,
    "indicatorId": "dt-nfl-nifc-cd",
    "rank": 56,
    "decimal": 0
  },
  {
    "countryId": "bi",
    "date": 2023,
    "value": -1250000,
    "indicatorId": "dt-nfl-nifc-cd",
    "rank": 57,
    "decimal": 0
  },
  {
    "countryId": "mv",
    "date": 2023,
    "value": -1363647.89,
    "indicatorId": "dt-nfl-nifc-cd",
    "rank": 58,
    "decimal": 0
  },
  {
    "countryId": "ht",
    "date": 2023,
    "value": -1910167.23,
    "indicatorId": "dt-nfl-nifc-cd",
    "rank": 59,
    "decimal": 0
  },
  {
    "countryId": "tj",
    "date": 2023,
    "value": -2242406.44,
    "indicatorId": "dt-nfl-nifc-cd",
    "rank": 60,
    "decimal": 0
  },
  {
    "countryId": "me",
    "date": 2023,
    "value": -2483784.04,
    "indicatorId": "dt-nfl-nifc-cd",
    "rank": 61,
    "decimal": 0
  },
  {
    "countryId": "bt",
    "date": 2019,
    "value": -3315789,
    "indicatorId": "dt-nfl-nifc-cd",
    "rank": 62,
    "decimal": 0
  },
  {
    "countryId": "km",
    "date": 2023,
    "value": -3562463.33,
    "indicatorId": "dt-nfl-nifc-cd",
    "rank": 63,
    "decimal": 0
  },
  {
    "countryId": "af",
    "date": 2022,
    "value": -3862459,
    "indicatorId": "dt-nfl-nifc-cd",
    "rank": 64,
    "decimal": 0
  },
  {
    "countryId": "rw",
    "date": 2023,
    "value": -4229186.77,
    "indicatorId": "dt-nfl-nifc-cd",
    "rank": 65,
    "decimal": 0
  },
  {
    "countryId": "hn",
    "date": 2023,
    "value": -4698556.34,
    "indicatorId": "dt-nfl-nifc-cd",
    "rank": 66,
    "decimal": 0
  },
  {
    "countryId": "am",
    "date": 2023,
    "value": -5289207.26,
    "indicatorId": "dt-nfl-nifc-cd",
    "rank": 67,
    "decimal": 0
  },
  {
    "countryId": "td",
    "date": 2023,
    "value": -5723237.2,
    "indicatorId": "dt-nfl-nifc-cd",
    "rank": 68,
    "decimal": 0
  },
  {
    "countryId": "by",
    "date": 2023,
    "value": -8000000,
    "indicatorId": "dt-nfl-nifc-cd",
    "rank": 69,
    "decimal": 0
  },
  {
    "countryId": "mu",
    "date": 2023,
    "value": -8333333.34,
    "indicatorId": "dt-nfl-nifc-cd",
    "rank": 70,
    "decimal": 0
  },
  {
    "countryId": "tg",
    "date": 2023,
    "value": -9651768.68,
    "indicatorId": "dt-nfl-nifc-cd",
    "rank": 71,
    "decimal": 0
  },
  {
    "countryId": "sb",
    "date": 2020,
    "value": -10263000,
    "indicatorId": "dt-nfl-nifc-cd",
    "rank": 72,
    "decimal": 0
  },
  {
    "countryId": "sc",
    "date": 2015,
    "value": -14545455,
    "indicatorId": "dt-nfl-nifc-cd",
    "rank": 73,
    "decimal": 0
  },
  {
    "countryId": "ua",
    "date": 2023,
    "value": -15147612.36,
    "indicatorId": "dt-nfl-nifc-cd",
    "rank": 74,
    "decimal": 0
  },
  {
    "countryId": "mk",
    "date": 2021,
    "value": -17559289,
    "indicatorId": "dt-nfl-nifc-cd",
    "rank": 75,
    "decimal": 0
  },
  {
    "countryId": "ye",
    "date": 2023,
    "value": -18320984.27,
    "indicatorId": "dt-nfl-nifc-cd",
    "rank": 76,
    "decimal": 0
  },
  {
    "countryId": "sv",
    "date": 2023,
    "value": -18706369,
    "indicatorId": "dt-nfl-nifc-cd",
    "rank": 77,
    "decimal": 0
  },
  {
    "countryId": "kh",
    "date": 2023,
    "value": -19996718.4,
    "indicatorId": "dt-nfl-nifc-cd",
    "rank": 78,
    "decimal": 0
  },
  {
    "countryId": "lb",
    "date": 2020,
    "value": -20115851,
    "indicatorId": "dt-nfl-nifc-cd",
    "rank": 79,
    "decimal": 0
  },
  {
    "countryId": "gn",
    "date": 2023,
    "value": -23146186.64,
    "indicatorId": "dt-nfl-nifc-cd",
    "rank": 80,
    "decimal": 0
  },
  {
    "countryId": "ug",
    "date": 2023,
    "value": -25611906.92,
    "indicatorId": "dt-nfl-nifc-cd",
    "rank": 81,
    "decimal": 0
  },
  {
    "countryId": "ni",
    "date": 2023,
    "value": -28399182.28,
    "indicatorId": "dt-nfl-nifc-cd",
    "rank": 82,
    "decimal": 0
  },
  {
    "countryId": "pg",
    "date": 2020,
    "value": -34285716,
    "indicatorId": "dt-nfl-nifc-cd",
    "rank": 83,
    "decimal": 0
  },
  {
    "countryId": "lk",
    "date": 2023,
    "value": -36674818.25,
    "indicatorId": "dt-nfl-nifc-cd",
    "rank": 84,
    "decimal": 0
  },
  {
    "countryId": "gy",
    "date": 2016,
    "value": -37751431,
    "indicatorId": "dt-nfl-nifc-cd",
    "rank": 85,
    "decimal": 0
  },
  {
    "countryId": "jo",
    "date": 2023,
    "value": -38027637.22,
    "indicatorId": "dt-nfl-nifc-cd",
    "rank": 86,
    "decimal": 0
  },
  {
    "countryId": "ao",
    "date": 2023,
    "value": -38888888.9,
    "indicatorId": "dt-nfl-nifc-cd",
    "rank": 87,
    "decimal": 0
  },
  {
    "countryId": "iq",
    "date": 2023,
    "value": -39240953.24,
    "indicatorId": "dt-nfl-nifc-cd",
    "rank": 88,
    "decimal": 0
  },
  {
    "countryId": "jm",
    "date": 2023,
    "value": -40000000,
    "indicatorId": "dt-nfl-nifc-cd",
    "rank": 89,
    "decimal": 0
  },
  {
    "countryId": "pk",
    "date": 2023,
    "value": -43693664.07,
    "indicatorId": "dt-nfl-nifc-cd",
    "rank": 90,
    "decimal": 0
  },
  {
    "countryId": "cr",
    "date": 2023,
    "value": -44766258.91,
    "indicatorId": "dt-nfl-nifc-cd",
    "rank": 91,
    "decimal": 0
  },
  {
    "countryId": "ge",
    "date": 2023,
    "value": -56346360.64,
    "indicatorId": "dt-nfl-nifc-cd",
    "rank": 92,
    "decimal": 0
  },
  {
    "countryId": "mm",
    "date": 2023,
    "value": -56432059.22,
    "indicatorId": "dt-nfl-nifc-cd",
    "rank": 93,
    "decimal": 0
  },
  {
    "countryId": "mr",
    "date": 2023,
    "value": -63066666.67,
    "indicatorId": "dt-nfl-nifc-cd",
    "rank": 94,
    "decimal": 0
  },
  {
    "countryId": "gh",
    "date": 2023,
    "value": -64113270.83,
    "indicatorId": "dt-nfl-nifc-cd",
    "rank": 95,
    "decimal": 0
  },
  {
    "countryId": "ar",
    "date": 2023,
    "value": -139947843.74,
    "indicatorId": "dt-nfl-nifc-cd",
    "rank": 96,
    "decimal": 0
  }
]